{"meta":{"app":"https://ctjs.rocks/","version":"3.2.0","image":"a2.png","format":"RGBA8888","size":{"w":2048,"h":2048},"scale":"1"},"frames":{"RED_BOX-NESTO_ACTIVITY-MSN_RESIDENTS_WORKSHOP@frame0":{"frame":{"x":1,"y":1,"w":1121,"h":1167},"rotated":false,"trimmed":false,"spriteSourceSize":{"x":0,"y":0,"w":1121,"h":1167},"sourceSize":{"w":1121,"h":1167},"anchor":{"x":0.49955396966993754,"y":0.4995715509854327},"shape":{"type":"rect","top":377,"bottom":405,"left":405,"right":375}}},"animations":{"RED_BOX-NESTO_ACTIVITY-MSN_RESIDENTS_WORKSHOP":["RED_BOX-NESTO_ACTIVITY-MSN_RESIDENTS_WORKSHOP@frame0"]}}
