<font>
    <info face="Geist-Regular_400" size="16" bold="0" italic="0" chasrset="" unicode="0" stretchH="100" smooth="1" aa="1" padding="0,0,0,0" spacing="1,1"/>
    <common lineHeight="18" base="16" scaleW="1024" scaleH="512" pages="1" packed="0"/>
    <pages>
        <page id="0" file="BdNGWmNGgrKJNN.png"/>
    </pages>
    <chars count="720">
        <char id="32" x="34" y="1" width="4" height="20" xoffset="0" yoffset="0" xadvance="4" page="0" chnl="0" letter="space"/>
        <char id="33" x="42" y="1" width="4" height="20" xoffset="0" yoffset="0" xadvance="4" page="0" chnl="0" letter="!"/>
        <char id="34" x="50" y="1" width="6" height="20" xoffset="0" yoffset="0" xadvance="6" page="0" chnl="0" letter="&quot;"/>
        <char id="35" x="60" y="1" width="8" height="20" xoffset="0" yoffset="0" xadvance="8" page="0" chnl="0" letter="#"/>
        <char id="36" x="72" y="1" width="11" height="20" xoffset="0" yoffset="0" xadvance="11" page="0" chnl="0" letter="$"/>
        <char id="37" x="87" y="1" width="13" height="20" xoffset="0" yoffset="0" xadvance="13" page="0" chnl="0" letter="%"/>
        <char id="38" x="104" y="1" width="10" height="20" xoffset="0" yoffset="0" xadvance="10" page="0" chnl="0" letter="&amp;"/>
        <char id="39" x="118" y="1" width="3" height="20" xoffset="0" yoffset="0" xadvance="3" page="0" chnl="0" letter="'"/>
        <char id="40" x="125" y="1" width="5" height="20" xoffset="0" yoffset="0" xadvance="5" page="0" chnl="0" letter="("/>
        <char id="41" x="134" y="1" width="5" height="20" xoffset="0" yoffset="0" xadvance="5" page="0" chnl="0" letter=")"/>
        <char id="42" x="143" y="1" width="7" height="20" xoffset="0" yoffset="0" xadvance="7" page="0" chnl="0" letter="*"/>
        <char id="43" x="154" y="1" width="10" height="20" xoffset="0" yoffset="0" xadvance="10" page="0" chnl="0" letter="+"/>
        <char id="44" x="168" y="1" width="4" height="20" xoffset="0" yoffset="0" xadvance="4" page="0" chnl="0" letter=","/>
        <char id="45" x="176" y="1" width="7" height="20" xoffset="0" yoffset="0" xadvance="7" page="0" chnl="0" letter="-"/>
        <char id="46" x="187" y="1" width="4" height="20" xoffset="0" yoffset="0" xadvance="4" page="0" chnl="0" letter="."/>
        <char id="47" x="195" y="1" width="8" height="20" xoffset="0" yoffset="0" xadvance="8" page="0" chnl="0" letter="/"/>
        <char id="48" x="207" y="1" width="11" height="20" xoffset="0" yoffset="0" xadvance="11" page="0" chnl="0" letter="0"/>
        <char id="49" x="222" y="1" width="7" height="20" xoffset="0" yoffset="0" xadvance="7" page="0" chnl="0" letter="1"/>
        <char id="50" x="233" y="1" width="10" height="20" xoffset="0" yoffset="0" xadvance="10" page="0" chnl="0" letter="2"/>
        <char id="51" x="247" y="1" width="10" height="20" xoffset="0" yoffset="0" xadvance="10" page="0" chnl="0" letter="3"/>
        <char id="52" x="261" y="1" width="11" height="20" xoffset="0" yoffset="0" xadvance="11" page="0" chnl="0" letter="4"/>
        <char id="53" x="276" y="1" width="11" height="20" xoffset="0" yoffset="0" xadvance="11" page="0" chnl="0" letter="5"/>
        <char id="54" x="291" y="1" width="10" height="20" xoffset="0" yoffset="0" xadvance="10" page="0" chnl="0" letter="6"/>
        <char id="55" x="305" y="1" width="10" height="20" xoffset="0" yoffset="0" xadvance="10" page="0" chnl="0" letter="7"/>
        <char id="56" x="319" y="1" width="10" height="20" xoffset="0" yoffset="0" xadvance="10" page="0" chnl="0" letter="8"/>
        <char id="57" x="333" y="1" width="10" height="20" xoffset="0" yoffset="0" xadvance="10" page="0" chnl="0" letter="9"/>
        <char id="58" x="347" y="1" width="5" height="20" xoffset="0" yoffset="0" xadvance="5" page="0" chnl="0" letter=":"/>
        <char id="59" x="356" y="1" width="5" height="20" xoffset="0" yoffset="0" xadvance="5" page="0" chnl="0" letter=";"/>
        <char id="60" x="365" y="1" width="9" height="20" xoffset="0" yoffset="0" xadvance="9" page="0" chnl="0" letter="&lt;"/>
        <char id="61" x="378" y="1" width="11" height="20" xoffset="0" yoffset="0" xadvance="11" page="0" chnl="0" letter="="/>
        <char id="62" x="393" y="1" width="9" height="20" xoffset="0" yoffset="0" xadvance="9" page="0" chnl="0" letter="&gt;"/>
        <char id="63" x="406" y="1" width="10" height="20" xoffset="0" yoffset="0" xadvance="10" page="0" chnl="0" letter="?"/>
        <char id="64" x="420" y="1" width="15" height="20" xoffset="0" yoffset="0" xadvance="15" page="0" chnl="0" letter="@"/>
        <char id="65" x="439" y="1" width="11" height="20" xoffset="0" yoffset="0" xadvance="11" page="0" chnl="0" letter="A"/>
        <char id="66" x="454" y="1" width="11" height="20" xoffset="0" yoffset="0" xadvance="11" page="0" chnl="0" letter="B"/>
        <char id="67" x="469" y="1" width="12" height="20" xoffset="0" yoffset="0" xadvance="12" page="0" chnl="0" letter="C"/>
        <char id="68" x="485" y="1" width="12" height="20" xoffset="0" yoffset="0" xadvance="12" page="0" chnl="0" letter="D"/>
        <char id="69" x="501" y="1" width="10" height="20" xoffset="0" yoffset="0" xadvance="10" page="0" chnl="0" letter="E"/>
        <char id="70" x="515" y="1" width="10" height="20" xoffset="0" yoffset="0" xadvance="10" page="0" chnl="0" letter="F"/>
        <char id="71" x="529" y="1" width="12" height="20" xoffset="0" yoffset="0" xadvance="12" page="0" chnl="0" letter="G"/>
        <char id="72" x="545" y="1" width="12" height="20" xoffset="0" yoffset="0" xadvance="12" page="0" chnl="0" letter="H"/>
        <char id="73" x="561" y="1" width="5" height="20" xoffset="0" yoffset="0" xadvance="5" page="0" chnl="0" letter="I"/>
        <char id="74" x="570" y="1" width="10" height="20" xoffset="0" yoffset="0" xadvance="10" page="0" chnl="0" letter="J"/>
        <char id="75" x="584" y="1" width="11" height="20" xoffset="0" yoffset="0" xadvance="11" page="0" chnl="0" letter="K"/>
        <char id="76" x="599" y="1" width="10" height="20" xoffset="0" yoffset="0" xadvance="10" page="0" chnl="0" letter="L"/>
        <char id="77" x="613" y="1" width="15" height="20" xoffset="0" yoffset="0" xadvance="15" page="0" chnl="0" letter="M"/>
        <char id="78" x="632" y="1" width="12" height="20" xoffset="0" yoffset="0" xadvance="12" page="0" chnl="0" letter="N"/>
        <char id="79" x="648" y="1" width="12" height="20" xoffset="0" yoffset="0" xadvance="12" page="0" chnl="0" letter="O"/>
        <char id="80" x="664" y="1" width="11" height="20" xoffset="0" yoffset="0" xadvance="11" page="0" chnl="0" letter="P"/>
        <char id="81" x="679" y="1" width="12" height="20" xoffset="0" yoffset="0" xadvance="12" page="0" chnl="0" letter="Q"/>
        <char id="82" x="695" y="1" width="11" height="20" xoffset="0" yoffset="0" xadvance="11" page="0" chnl="0" letter="R"/>
        <char id="83" x="710" y="1" width="11" height="20" xoffset="0" yoffset="0" xadvance="11" page="0" chnl="0" letter="S"/>
        <char id="84" x="725" y="1" width="10" height="20" xoffset="0" yoffset="0" xadvance="10" page="0" chnl="0" letter="T"/>
        <char id="85" x="739" y="1" width="12" height="20" xoffset="0" yoffset="0" xadvance="12" page="0" chnl="0" letter="U"/>
        <char id="86" x="755" y="1" width="11" height="20" xoffset="0" yoffset="0" xadvance="11" page="0" chnl="0" letter="V"/>
        <char id="87" x="770" y="1" width="15" height="20" xoffset="0" yoffset="0" xadvance="15" page="0" chnl="0" letter="W"/>
        <char id="88" x="789" y="1" width="11" height="20" xoffset="0" yoffset="0" xadvance="11" page="0" chnl="0" letter="X"/>
        <char id="89" x="804" y="1" width="11" height="20" xoffset="0" yoffset="0" xadvance="11" page="0" chnl="0" letter="Y"/>
        <char id="90" x="819" y="1" width="9" height="20" xoffset="0" yoffset="0" xadvance="9" page="0" chnl="0" letter="Z"/>
        <char id="91" x="832" y="1" width="6" height="20" xoffset="0" yoffset="0" xadvance="6" page="0" chnl="0" letter="["/>
        <char id="92" x="842" y="1" width="8" height="20" xoffset="0" yoffset="0" xadvance="8" page="0" chnl="0" letter="\"/>
        <char id="93" x="854" y="1" width="6" height="20" xoffset="0" yoffset="0" xadvance="6" page="0" chnl="0" letter="]"/>
        <char id="94" x="864" y="1" width="7" height="20" xoffset="0" yoffset="0" xadvance="7" page="0" chnl="0" letter="^"/>
        <char id="95" x="875" y="1" width="10" height="20" xoffset="0" yoffset="0" xadvance="10" page="0" chnl="0" letter="_"/>
        <char id="96" x="889" y="1" width="4" height="20" xoffset="0" yoffset="0" xadvance="4" page="0" chnl="0" letter="`"/>
        <char id="97" x="897" y="1" width="10" height="20" xoffset="0" yoffset="0" xadvance="10" page="0" chnl="0" letter="a"/>
        <char id="98" x="911" y="1" width="10" height="20" xoffset="0" yoffset="0" xadvance="10" page="0" chnl="0" letter="b"/>
        <char id="99" x="925" y="1" width="9" height="20" xoffset="0" yoffset="0" xadvance="9" page="0" chnl="0" letter="c"/>
        <char id="100" x="938" y="1" width="10" height="20" xoffset="0" yoffset="0" xadvance="10" page="0" chnl="0" letter="d"/>
        <char id="101" x="952" y="1" width="10" height="20" xoffset="0" yoffset="0" xadvance="10" page="0" chnl="0" letter="e"/>
        <char id="102" x="966" y="1" width="7" height="20" xoffset="0" yoffset="0" xadvance="7" page="0" chnl="0" letter="f"/>
        <char id="103" x="977" y="1" width="10" height="20" xoffset="0" yoffset="0" xadvance="10" page="0" chnl="0" letter="g"/>
        <char id="104" x="991" y="1" width="10" height="20" xoffset="0" yoffset="0" xadvance="10" page="0" chnl="0" letter="h"/>
        <char id="105" x="1005" y="1" width="4" height="20" xoffset="0" yoffset="0" xadvance="4" page="0" chnl="0" letter="i"/>
        <char id="106" x="1013" y="1" width="5" height="20" xoffset="0" yoffset="0" xadvance="5" page="0" chnl="0" letter="j"/>
        <char id="107" x="1" y="25" width="10" height="20" xoffset="0" yoffset="0" xadvance="10" page="0" chnl="0" letter="k"/>
        <char id="108" x="15" y="25" width="5" height="20" xoffset="0" yoffset="0" xadvance="5" page="0" chnl="0" letter="l"/>
        <char id="109" x="24" y="25" width="15" height="20" xoffset="0" yoffset="0" xadvance="15" page="0" chnl="0" letter="m"/>
        <char id="110" x="43" y="25" width="10" height="20" xoffset="0" yoffset="0" xadvance="10" page="0" chnl="0" letter="n"/>
        <char id="111" x="57" y="25" width="10" height="20" xoffset="0" yoffset="0" xadvance="10" page="0" chnl="0" letter="o"/>
        <char id="112" x="71" y="25" width="10" height="20" xoffset="0" yoffset="0" xadvance="10" page="0" chnl="0" letter="p"/>
        <char id="113" x="85" y="25" width="10" height="20" xoffset="0" yoffset="0" xadvance="10" page="0" chnl="0" letter="q"/>
        <char id="114" x="99" y="25" width="7" height="20" xoffset="0" yoffset="0" xadvance="7" page="0" chnl="0" letter="r"/>
        <char id="115" x="110" y="25" width="9" height="20" xoffset="0" yoffset="0" xadvance="9" page="0" chnl="0" letter="s"/>
        <char id="116" x="123" y="25" width="7" height="20" xoffset="0" yoffset="0" xadvance="7" page="0" chnl="0" letter="t"/>
        <char id="117" x="134" y="25" width="10" height="20" xoffset="0" yoffset="0" xadvance="10" page="0" chnl="0" letter="u"/>
        <char id="118" x="148" y="25" width="9" height="20" xoffset="0" yoffset="0" xadvance="9" page="0" chnl="0" letter="v"/>
        <char id="119" x="161" y="25" width="14" height="20" xoffset="0" yoffset="0" xadvance="14" page="0" chnl="0" letter="w"/>
        <char id="120" x="179" y="25" width="10" height="20" xoffset="0" yoffset="0" xadvance="10" page="0" chnl="0" letter="x"/>
        <char id="121" x="193" y="25" width="9" height="20" xoffset="0" yoffset="0" xadvance="9" page="0" chnl="0" letter="y"/>
        <char id="122" x="206" y="25" width="9" height="20" xoffset="0" yoffset="0" xadvance="9" page="0" chnl="0" letter="z"/>
        <char id="123" x="219" y="25" width="7" height="20" xoffset="0" yoffset="0" xadvance="7" page="0" chnl="0" letter="{"/>
        <char id="124" x="230" y="25" width="5" height="20" xoffset="0" yoffset="0" xadvance="5" page="0" chnl="0" letter="|"/>
        <char id="125" x="239" y="25" width="7" height="20" xoffset="0" yoffset="0" xadvance="7" page="0" chnl="0" letter="}"/>
        <char id="126" x="250" y="25" width="9" height="20" xoffset="0" yoffset="0" xadvance="9" page="0" chnl="0" letter="~"/>
        <char id="160" x="263" y="25" width="4" height="20" xoffset="0" yoffset="0" xadvance="4" page="0" chnl="0" letter=" "/>
        <char id="161" x="271" y="25" width="4" height="20" xoffset="0" yoffset="0" xadvance="4" page="0" chnl="0" letter="¡"/>
        <char id="162" x="279" y="25" width="9" height="20" xoffset="0" yoffset="0" xadvance="9" page="0" chnl="0" letter="¢"/>
        <char id="163" x="292" y="25" width="10" height="20" xoffset="0" yoffset="0" xadvance="10" page="0" chnl="0" letter="£"/>
        <char id="164" x="306" y="25" width="10" height="20" xoffset="0" yoffset="0" xadvance="10" page="0" chnl="0" letter="¤"/>
        <char id="165" x="320" y="25" width="11" height="20" xoffset="0" yoffset="0" xadvance="11" page="0" chnl="0" letter="¥"/>
        <char id="166" x="335" y="25" width="5" height="20" xoffset="0" yoffset="0" xadvance="5" page="0" chnl="0" letter="¦"/>
        <char id="167" x="344" y="25" width="9" height="20" xoffset="0" yoffset="0" xadvance="9" page="0" chnl="0" letter="§"/>
        <char id="168" x="357" y="25" width="6" height="20" xoffset="0" yoffset="0" xadvance="6" page="0" chnl="0" letter="¨"/>
        <char id="169" x="367" y="25" width="14" height="20" xoffset="0" yoffset="0" xadvance="14" page="0" chnl="0" letter="©"/>
        <char id="170" x="385" y="25" width="10" height="20" xoffset="0" yoffset="0" xadvance="10" page="0" chnl="0" letter="ª"/>
        <char id="171" x="399" y="25" width="9" height="20" xoffset="0" yoffset="0" xadvance="9" page="0" chnl="0" letter="«"/>
        <char id="172" x="412" y="25" width="8" height="20" xoffset="0" yoffset="0" xadvance="8" page="0" chnl="0" letter="¬"/>
        <char id="173" x="424" y="25" width="7" height="20" xoffset="0" yoffset="0" xadvance="7" page="0" chnl="0" letter="­"/>
        <char id="174" x="435" y="25" width="10" height="20" xoffset="0" yoffset="0" xadvance="10" page="0" chnl="0" letter="®"/>
        <char id="175" x="449" y="25" width="6" height="20" xoffset="0" yoffset="0" xadvance="6" page="0" chnl="0" letter="¯"/>
        <char id="176" x="459" y="25" width="7" height="20" xoffset="0" yoffset="0" xadvance="7" page="0" chnl="0" letter="°"/>
        <char id="177" x="470" y="25" width="10" height="20" xoffset="0" yoffset="0" xadvance="10" page="0" chnl="0" letter="±"/>
        <char id="178" x="484" y="25" width="10" height="20" xoffset="0" yoffset="0" xadvance="10" page="0" chnl="0" letter="²"/>
        <char id="179" x="498" y="25" width="10" height="20" xoffset="0" yoffset="0" xadvance="10" page="0" chnl="0" letter="³"/>
        <char id="180" x="512" y="25" width="4" height="20" xoffset="0" yoffset="0" xadvance="4" page="0" chnl="0" letter="´"/>
        <char id="181" x="520" y="25" width="10" height="20" xoffset="0" yoffset="0" xadvance="10" page="0" chnl="0" letter="µ"/>
        <char id="182" x="534" y="25" width="10" height="20" xoffset="0" yoffset="0" xadvance="10" page="0" chnl="0" letter="¶"/>
        <char id="183" x="548" y="25" width="4" height="20" xoffset="0" yoffset="0" xadvance="4" page="0" chnl="0" letter="·"/>
        <char id="184" x="556" y="25" width="5" height="20" xoffset="0" yoffset="0" xadvance="5" page="0" chnl="0" letter="¸"/>
        <char id="185" x="565" y="25" width="10" height="20" xoffset="0" yoffset="0" xadvance="10" page="0" chnl="0" letter="¹"/>
        <char id="186" x="579" y="25" width="10" height="20" xoffset="0" yoffset="0" xadvance="10" page="0" chnl="0" letter="º"/>
        <char id="187" x="593" y="25" width="9" height="20" xoffset="0" yoffset="0" xadvance="9" page="0" chnl="0" letter="»"/>
        <char id="188" x="606" y="25" width="16" height="20" xoffset="0" yoffset="0" xadvance="16" page="0" chnl="0" letter="¼"/>
        <char id="189" x="626" y="25" width="16" height="20" xoffset="0" yoffset="0" xadvance="16" page="0" chnl="0" letter="½"/>
        <char id="190" x="646" y="25" width="16" height="20" xoffset="0" yoffset="0" xadvance="16" page="0" chnl="0" letter="¾"/>
        <char id="191" x="666" y="25" width="10" height="20" xoffset="0" yoffset="0" xadvance="10" page="0" chnl="0" letter="¿"/>
        <char id="192" x="680" y="25" width="11" height="20" xoffset="0" yoffset="0" xadvance="11" page="0" chnl="0" letter="À"/>
        <char id="193" x="695" y="25" width="11" height="20" xoffset="0" yoffset="0" xadvance="11" page="0" chnl="0" letter="Á"/>
        <char id="194" x="710" y="25" width="11" height="20" xoffset="0" yoffset="0" xadvance="11" page="0" chnl="0" letter="Â"/>
        <char id="195" x="725" y="25" width="11" height="20" xoffset="0" yoffset="0" xadvance="11" page="0" chnl="0" letter="Ã"/>
        <char id="196" x="740" y="25" width="11" height="20" xoffset="0" yoffset="0" xadvance="11" page="0" chnl="0" letter="Ä"/>
        <char id="197" x="755" y="25" width="11" height="20" xoffset="0" yoffset="0" xadvance="11" page="0" chnl="0" letter="Å"/>
        <char id="198" x="770" y="25" width="16" height="20" xoffset="0" yoffset="0" xadvance="16" page="0" chnl="0" letter="Æ"/>
        <char id="199" x="790" y="25" width="12" height="20" xoffset="0" yoffset="0" xadvance="12" page="0" chnl="0" letter="Ç"/>
        <char id="200" x="806" y="25" width="10" height="20" xoffset="0" yoffset="0" xadvance="10" page="0" chnl="0" letter="È"/>
        <char id="201" x="820" y="25" width="10" height="20" xoffset="0" yoffset="0" xadvance="10" page="0" chnl="0" letter="É"/>
        <char id="202" x="834" y="25" width="10" height="20" xoffset="0" yoffset="0" xadvance="10" page="0" chnl="0" letter="Ê"/>
        <char id="203" x="848" y="25" width="10" height="20" xoffset="0" yoffset="0" xadvance="10" page="0" chnl="0" letter="Ë"/>
        <char id="204" x="862" y="25" width="5" height="20" xoffset="0" yoffset="0" xadvance="5" page="0" chnl="0" letter="Ì"/>
        <char id="205" x="871" y="25" width="5" height="20" xoffset="0" yoffset="0" xadvance="5" page="0" chnl="0" letter="Í"/>
        <char id="206" x="880" y="25" width="5" height="20" xoffset="0" yoffset="0" xadvance="5" page="0" chnl="0" letter="Î"/>
        <char id="207" x="889" y="25" width="5" height="20" xoffset="0" yoffset="0" xadvance="5" page="0" chnl="0" letter="Ï"/>
        <char id="208" x="898" y="25" width="13" height="20" xoffset="0" yoffset="0" xadvance="13" page="0" chnl="0" letter="Ð"/>
        <char id="209" x="915" y="25" width="12" height="20" xoffset="0" yoffset="0" xadvance="12" page="0" chnl="0" letter="Ñ"/>
        <char id="210" x="931" y="25" width="12" height="20" xoffset="0" yoffset="0" xadvance="12" page="0" chnl="0" letter="Ò"/>
        <char id="211" x="947" y="25" width="12" height="20" xoffset="0" yoffset="0" xadvance="12" page="0" chnl="0" letter="Ó"/>
        <char id="212" x="963" y="25" width="12" height="20" xoffset="0" yoffset="0" xadvance="12" page="0" chnl="0" letter="Ô"/>
        <char id="213" x="979" y="25" width="12" height="20" xoffset="0" yoffset="0" xadvance="12" page="0" chnl="0" letter="Õ"/>
        <char id="214" x="995" y="25" width="12" height="20" xoffset="0" yoffset="0" xadvance="12" page="0" chnl="0" letter="Ö"/>
        <char id="215" x="1011" y="25" width="8" height="20" xoffset="0" yoffset="0" xadvance="8" page="0" chnl="0" letter="×"/>
        <char id="216" x="1" y="49" width="13" height="20" xoffset="0" yoffset="0" xadvance="13" page="0" chnl="0" letter="Ø"/>
        <char id="217" x="18" y="49" width="12" height="20" xoffset="0" yoffset="0" xadvance="12" page="0" chnl="0" letter="Ù"/>
        <char id="218" x="34" y="49" width="12" height="20" xoffset="0" yoffset="0" xadvance="12" page="0" chnl="0" letter="Ú"/>
        <char id="219" x="50" y="49" width="12" height="20" xoffset="0" yoffset="0" xadvance="12" page="0" chnl="0" letter="Û"/>
        <char id="220" x="66" y="49" width="12" height="20" xoffset="0" yoffset="0" xadvance="12" page="0" chnl="0" letter="Ü"/>
        <char id="221" x="82" y="49" width="11" height="20" xoffset="0" yoffset="0" xadvance="11" page="0" chnl="0" letter="Ý"/>
        <char id="222" x="97" y="49" width="10" height="20" xoffset="0" yoffset="0" xadvance="10" page="0" chnl="0" letter="Þ"/>
        <char id="223" x="111" y="49" width="10" height="20" xoffset="0" yoffset="0" xadvance="10" page="0" chnl="0" letter="ß"/>
        <char id="224" x="125" y="49" width="10" height="20" xoffset="0" yoffset="0" xadvance="10" page="0" chnl="0" letter="à"/>
        <char id="225" x="139" y="49" width="10" height="20" xoffset="0" yoffset="0" xadvance="10" page="0" chnl="0" letter="á"/>
        <char id="226" x="153" y="49" width="10" height="20" xoffset="0" yoffset="0" xadvance="10" page="0" chnl="0" letter="â"/>
        <char id="227" x="167" y="49" width="10" height="20" xoffset="0" yoffset="0" xadvance="10" page="0" chnl="0" letter="ã"/>
        <char id="228" x="181" y="49" width="10" height="20" xoffset="0" yoffset="0" xadvance="10" page="0" chnl="0" letter="ä"/>
        <char id="229" x="195" y="49" width="10" height="20" xoffset="0" yoffset="0" xadvance="10" page="0" chnl="0" letter="å"/>
        <char id="230" x="209" y="49" width="15" height="20" xoffset="0" yoffset="0" xadvance="15" page="0" chnl="0" letter="æ"/>
        <char id="231" x="228" y="49" width="9" height="20" xoffset="0" yoffset="0" xadvance="9" page="0" chnl="0" letter="ç"/>
        <char id="232" x="241" y="49" width="10" height="20" xoffset="0" yoffset="0" xadvance="10" page="0" chnl="0" letter="è"/>
        <char id="233" x="255" y="49" width="10" height="20" xoffset="0" yoffset="0" xadvance="10" page="0" chnl="0" letter="é"/>
        <char id="234" x="269" y="49" width="10" height="20" xoffset="0" yoffset="0" xadvance="10" page="0" chnl="0" letter="ê"/>
        <char id="235" x="283" y="49" width="10" height="20" xoffset="0" yoffset="0" xadvance="10" page="0" chnl="0" letter="ë"/>
        <char id="236" x="297" y="49" width="4" height="20" xoffset="0" yoffset="0" xadvance="4" page="0" chnl="0" letter="ì"/>
        <char id="237" x="305" y="49" width="4" height="20" xoffset="0" yoffset="0" xadvance="4" page="0" chnl="0" letter="í"/>
        <char id="238" x="313" y="49" width="4" height="20" xoffset="0" yoffset="0" xadvance="4" page="0" chnl="0" letter="î"/>
        <char id="239" x="321" y="49" width="4" height="20" xoffset="0" yoffset="0" xadvance="4" page="0" chnl="0" letter="ï"/>
        <char id="240" x="329" y="49" width="10" height="20" xoffset="0" yoffset="0" xadvance="10" page="0" chnl="0" letter="ð"/>
        <char id="241" x="343" y="49" width="10" height="20" xoffset="0" yoffset="0" xadvance="10" page="0" chnl="0" letter="ñ"/>
        <char id="242" x="357" y="49" width="10" height="20" xoffset="0" yoffset="0" xadvance="10" page="0" chnl="0" letter="ò"/>
        <char id="243" x="371" y="49" width="10" height="20" xoffset="0" yoffset="0" xadvance="10" page="0" chnl="0" letter="ó"/>
        <char id="244" x="385" y="49" width="10" height="20" xoffset="0" yoffset="0" xadvance="10" page="0" chnl="0" letter="ô"/>
        <char id="245" x="399" y="49" width="10" height="20" xoffset="0" yoffset="0" xadvance="10" page="0" chnl="0" letter="õ"/>
        <char id="246" x="413" y="49" width="10" height="20" xoffset="0" yoffset="0" xadvance="10" page="0" chnl="0" letter="ö"/>
        <char id="247" x="427" y="49" width="10" height="20" xoffset="0" yoffset="0" xadvance="10" page="0" chnl="0" letter="÷"/>
        <char id="248" x="441" y="49" width="10" height="20" xoffset="0" yoffset="0" xadvance="10" page="0" chnl="0" letter="ø"/>
        <char id="249" x="455" y="49" width="10" height="20" xoffset="0" yoffset="0" xadvance="10" page="0" chnl="0" letter="ù"/>
        <char id="250" x="469" y="49" width="10" height="20" xoffset="0" yoffset="0" xadvance="10" page="0" chnl="0" letter="ú"/>
        <char id="251" x="483" y="49" width="10" height="20" xoffset="0" yoffset="0" xadvance="10" page="0" chnl="0" letter="û"/>
        <char id="252" x="497" y="49" width="10" height="20" xoffset="0" yoffset="0" xadvance="10" page="0" chnl="0" letter="ü"/>
        <char id="253" x="511" y="49" width="9" height="20" xoffset="0" yoffset="0" xadvance="9" page="0" chnl="0" letter="ý"/>
        <char id="254" x="524" y="49" width="10" height="20" xoffset="0" yoffset="0" xadvance="10" page="0" chnl="0" letter="þ"/>
        <char id="255" x="538" y="49" width="9" height="20" xoffset="0" yoffset="0" xadvance="9" page="0" chnl="0" letter="ÿ"/>
        <char id="256" x="551" y="49" width="11" height="20" xoffset="0" yoffset="0" xadvance="11" page="0" chnl="0" letter="Ā"/>
        <char id="257" x="566" y="49" width="10" height="20" xoffset="0" yoffset="0" xadvance="10" page="0" chnl="0" letter="ā"/>
        <char id="258" x="580" y="49" width="11" height="20" xoffset="0" yoffset="0" xadvance="11" page="0" chnl="0" letter="Ă"/>
        <char id="259" x="595" y="49" width="10" height="20" xoffset="0" yoffset="0" xadvance="10" page="0" chnl="0" letter="ă"/>
        <char id="260" x="609" y="49" width="12" height="20" xoffset="0" yoffset="0" xadvance="12" page="0" chnl="0" letter="Ą"/>
        <char id="261" x="625" y="49" width="10" height="20" xoffset="0" yoffset="0" xadvance="10" page="0" chnl="0" letter="ą"/>
        <char id="262" x="639" y="49" width="12" height="20" xoffset="0" yoffset="0" xadvance="12" page="0" chnl="0" letter="Ć"/>
        <char id="263" x="655" y="49" width="9" height="20" xoffset="0" yoffset="0" xadvance="9" page="0" chnl="0" letter="ć"/>
        <char id="264" x="668" y="49" width="12" height="20" xoffset="0" yoffset="0" xadvance="12" page="0" chnl="0" letter="Ĉ"/>
        <char id="265" x="684" y="49" width="9" height="20" xoffset="0" yoffset="0" xadvance="9" page="0" chnl="0" letter="ĉ"/>
        <char id="266" x="697" y="49" width="12" height="20" xoffset="0" yoffset="0" xadvance="12" page="0" chnl="0" letter="Ċ"/>
        <char id="267" x="713" y="49" width="9" height="20" xoffset="0" yoffset="0" xadvance="9" page="0" chnl="0" letter="ċ"/>
        <char id="268" x="726" y="49" width="12" height="20" xoffset="0" yoffset="0" xadvance="12" page="0" chnl="0" letter="Č"/>
        <char id="269" x="742" y="49" width="9" height="20" xoffset="0" yoffset="0" xadvance="9" page="0" chnl="0" letter="č"/>
        <char id="270" x="755" y="49" width="12" height="20" xoffset="0" yoffset="0" xadvance="12" page="0" chnl="0" letter="Ď"/>
        <char id="271" x="771" y="49" width="12" height="20" xoffset="0" yoffset="0" xadvance="12" page="0" chnl="0" letter="ď"/>
        <char id="272" x="787" y="49" width="13" height="20" xoffset="0" yoffset="0" xadvance="13" page="0" chnl="0" letter="Đ"/>
        <char id="273" x="804" y="49" width="11" height="20" xoffset="0" yoffset="0" xadvance="11" page="0" chnl="0" letter="đ"/>
        <char id="274" x="819" y="49" width="10" height="20" xoffset="0" yoffset="0" xadvance="10" page="0" chnl="0" letter="Ē"/>
        <char id="275" x="833" y="49" width="10" height="20" xoffset="0" yoffset="0" xadvance="10" page="0" chnl="0" letter="ē"/>
        <char id="278" x="847" y="49" width="10" height="20" xoffset="0" yoffset="0" xadvance="10" page="0" chnl="0" letter="Ė"/>
        <char id="279" x="861" y="49" width="10" height="20" xoffset="0" yoffset="0" xadvance="10" page="0" chnl="0" letter="ė"/>
        <char id="280" x="875" y="49" width="10" height="20" xoffset="0" yoffset="0" xadvance="10" page="0" chnl="0" letter="Ę"/>
        <char id="281" x="889" y="49" width="10" height="20" xoffset="0" yoffset="0" xadvance="10" page="0" chnl="0" letter="ę"/>
        <char id="282" x="903" y="49" width="10" height="20" xoffset="0" yoffset="0" xadvance="10" page="0" chnl="0" letter="Ě"/>
        <char id="283" x="917" y="49" width="10" height="20" xoffset="0" yoffset="0" xadvance="10" page="0" chnl="0" letter="ě"/>
        <char id="284" x="931" y="49" width="12" height="20" xoffset="0" yoffset="0" xadvance="12" page="0" chnl="0" letter="Ĝ"/>
        <char id="285" x="947" y="49" width="10" height="20" xoffset="0" yoffset="0" xadvance="10" page="0" chnl="0" letter="ĝ"/>
        <char id="286" x="961" y="49" width="12" height="20" xoffset="0" yoffset="0" xadvance="12" page="0" chnl="0" letter="Ğ"/>
        <char id="287" x="977" y="49" width="10" height="20" xoffset="0" yoffset="0" xadvance="10" page="0" chnl="0" letter="ğ"/>
        <char id="288" x="991" y="49" width="12" height="20" xoffset="0" yoffset="0" xadvance="12" page="0" chnl="0" letter="Ġ"/>
        <char id="289" x="1007" y="49" width="10" height="20" xoffset="0" yoffset="0" xadvance="10" page="0" chnl="0" letter="ġ"/>
        <char id="290" x="1" y="73" width="12" height="20" xoffset="0" yoffset="0" xadvance="12" page="0" chnl="0" letter="Ģ"/>
        <char id="291" x="17" y="73" width="10" height="20" xoffset="0" yoffset="0" xadvance="10" page="0" chnl="0" letter="ģ"/>
        <char id="292" x="31" y="73" width="12" height="20" xoffset="0" yoffset="0" xadvance="12" page="0" chnl="0" letter="Ĥ"/>
        <char id="293" x="47" y="73" width="10" height="20" xoffset="0" yoffset="0" xadvance="10" page="0" chnl="0" letter="ĥ"/>
        <char id="294" x="61" y="73" width="14" height="20" xoffset="0" yoffset="0" xadvance="14" page="0" chnl="0" letter="Ħ"/>
        <char id="295" x="79" y="73" width="10" height="20" xoffset="0" yoffset="0" xadvance="10" page="0" chnl="0" letter="ħ"/>
        <char id="296" x="93" y="73" width="5" height="20" xoffset="0" yoffset="0" xadvance="5" page="0" chnl="0" letter="Ĩ"/>
        <char id="297" x="102" y="73" width="4" height="20" xoffset="0" yoffset="0" xadvance="4" page="0" chnl="0" letter="ĩ"/>
        <char id="298" x="110" y="73" width="5" height="20" xoffset="0" yoffset="0" xadvance="5" page="0" chnl="0" letter="Ī"/>
        <char id="299" x="119" y="73" width="4" height="20" xoffset="0" yoffset="0" xadvance="4" page="0" chnl="0" letter="ī"/>
        <char id="302" x="127" y="73" width="5" height="20" xoffset="0" yoffset="0" xadvance="5" page="0" chnl="0" letter="Į"/>
        <char id="303" x="136" y="73" width="4" height="20" xoffset="0" yoffset="0" xadvance="4" page="0" chnl="0" letter="į"/>
        <char id="304" x="144" y="73" width="5" height="20" xoffset="0" yoffset="0" xadvance="5" page="0" chnl="0" letter="İ"/>
        <char id="305" x="153" y="73" width="4" height="20" xoffset="0" yoffset="0" xadvance="4" page="0" chnl="0" letter="ı"/>
        <char id="306" x="161" y="73" width="13" height="20" xoffset="0" yoffset="0" xadvance="13" page="0" chnl="0" letter="Ĳ"/>
        <char id="307" x="178" y="73" width="8" height="20" xoffset="0" yoffset="0" xadvance="8" page="0" chnl="0" letter="ĳ"/>
        <char id="308" x="190" y="73" width="10" height="20" xoffset="0" yoffset="0" xadvance="10" page="0" chnl="0" letter="Ĵ"/>
        <char id="309" x="204" y="73" width="5" height="20" xoffset="0" yoffset="0" xadvance="5" page="0" chnl="0" letter="ĵ"/>
        <char id="310" x="213" y="73" width="11" height="20" xoffset="0" yoffset="0" xadvance="11" page="0" chnl="0" letter="Ķ"/>
        <char id="311" x="228" y="73" width="10" height="20" xoffset="0" yoffset="0" xadvance="10" page="0" chnl="0" letter="ķ"/>
        <char id="313" x="242" y="73" width="10" height="20" xoffset="0" yoffset="0" xadvance="10" page="0" chnl="0" letter="Ĺ"/>
        <char id="314" x="256" y="73" width="5" height="20" xoffset="0" yoffset="0" xadvance="5" page="0" chnl="0" letter="ĺ"/>
        <char id="315" x="265" y="73" width="10" height="20" xoffset="0" yoffset="0" xadvance="10" page="0" chnl="0" letter="Ļ"/>
        <char id="316" x="279" y="73" width="5" height="20" xoffset="0" yoffset="0" xadvance="5" page="0" chnl="0" letter="ļ"/>
        <char id="317" x="288" y="73" width="10" height="20" xoffset="0" yoffset="0" xadvance="10" page="0" chnl="0" letter="Ľ"/>
        <char id="318" x="302" y="73" width="6" height="20" xoffset="0" yoffset="0" xadvance="6" page="0" chnl="0" letter="ľ"/>
        <char id="321" x="312" y="73" width="10" height="20" xoffset="0" yoffset="0" xadvance="10" page="0" chnl="0" letter="Ł"/>
        <char id="322" x="326" y="73" width="7" height="20" xoffset="0" yoffset="0" xadvance="7" page="0" chnl="0" letter="ł"/>
        <char id="323" x="337" y="73" width="12" height="20" xoffset="0" yoffset="0" xadvance="12" page="0" chnl="0" letter="Ń"/>
        <char id="324" x="353" y="73" width="10" height="20" xoffset="0" yoffset="0" xadvance="10" page="0" chnl="0" letter="ń"/>
        <char id="325" x="367" y="73" width="12" height="20" xoffset="0" yoffset="0" xadvance="12" page="0" chnl="0" letter="Ņ"/>
        <char id="326" x="383" y="73" width="10" height="20" xoffset="0" yoffset="0" xadvance="10" page="0" chnl="0" letter="ņ"/>
        <char id="327" x="397" y="73" width="12" height="20" xoffset="0" yoffset="0" xadvance="12" page="0" chnl="0" letter="Ň"/>
        <char id="328" x="413" y="73" width="10" height="20" xoffset="0" yoffset="0" xadvance="10" page="0" chnl="0" letter="ň"/>
        <char id="330" x="427" y="73" width="12" height="20" xoffset="0" yoffset="0" xadvance="12" page="0" chnl="0" letter="Ŋ"/>
        <char id="331" x="443" y="73" width="10" height="20" xoffset="0" yoffset="0" xadvance="10" page="0" chnl="0" letter="ŋ"/>
        <char id="332" x="457" y="73" width="12" height="20" xoffset="0" yoffset="0" xadvance="12" page="0" chnl="0" letter="Ō"/>
        <char id="333" x="473" y="73" width="10" height="20" xoffset="0" yoffset="0" xadvance="10" page="0" chnl="0" letter="ō"/>
        <char id="336" x="487" y="73" width="12" height="20" xoffset="0" yoffset="0" xadvance="12" page="0" chnl="0" letter="Ő"/>
        <char id="337" x="503" y="73" width="10" height="20" xoffset="0" yoffset="0" xadvance="10" page="0" chnl="0" letter="ő"/>
        <char id="338" x="517" y="73" width="18" height="20" xoffset="0" yoffset="0" xadvance="18" page="0" chnl="0" letter="Œ"/>
        <char id="339" x="539" y="73" width="16" height="20" xoffset="0" yoffset="0" xadvance="16" page="0" chnl="0" letter="œ"/>
        <char id="340" x="559" y="73" width="11" height="20" xoffset="0" yoffset="0" xadvance="11" page="0" chnl="0" letter="Ŕ"/>
        <char id="341" x="574" y="73" width="7" height="20" xoffset="0" yoffset="0" xadvance="7" page="0" chnl="0" letter="ŕ"/>
        <char id="342" x="585" y="73" width="11" height="20" xoffset="0" yoffset="0" xadvance="11" page="0" chnl="0" letter="Ŗ"/>
        <char id="343" x="600" y="73" width="7" height="20" xoffset="0" yoffset="0" xadvance="7" page="0" chnl="0" letter="ŗ"/>
        <char id="344" x="611" y="73" width="11" height="20" xoffset="0" yoffset="0" xadvance="11" page="0" chnl="0" letter="Ř"/>
        <char id="345" x="626" y="73" width="7" height="20" xoffset="0" yoffset="0" xadvance="7" page="0" chnl="0" letter="ř"/>
        <char id="346" x="637" y="73" width="11" height="20" xoffset="0" yoffset="0" xadvance="11" page="0" chnl="0" letter="Ś"/>
        <char id="347" x="652" y="73" width="9" height="20" xoffset="0" yoffset="0" xadvance="9" page="0" chnl="0" letter="ś"/>
        <char id="348" x="665" y="73" width="11" height="20" xoffset="0" yoffset="0" xadvance="11" page="0" chnl="0" letter="Ŝ"/>
        <char id="349" x="680" y="73" width="9" height="20" xoffset="0" yoffset="0" xadvance="9" page="0" chnl="0" letter="ŝ"/>
        <char id="350" x="693" y="73" width="11" height="20" xoffset="0" yoffset="0" xadvance="11" page="0" chnl="0" letter="Ş"/>
        <char id="351" x="708" y="73" width="9" height="20" xoffset="0" yoffset="0" xadvance="9" page="0" chnl="0" letter="ş"/>
        <char id="352" x="721" y="73" width="11" height="20" xoffset="0" yoffset="0" xadvance="11" page="0" chnl="0" letter="Š"/>
        <char id="353" x="736" y="73" width="9" height="20" xoffset="0" yoffset="0" xadvance="9" page="0" chnl="0" letter="š"/>
        <char id="354" x="749" y="73" width="10" height="20" xoffset="0" yoffset="0" xadvance="10" page="0" chnl="0" letter="Ţ"/>
        <char id="355" x="763" y="73" width="7" height="20" xoffset="0" yoffset="0" xadvance="7" page="0" chnl="0" letter="ţ"/>
        <char id="356" x="774" y="73" width="10" height="20" xoffset="0" yoffset="0" xadvance="10" page="0" chnl="0" letter="Ť"/>
        <char id="357" x="788" y="73" width="7" height="20" xoffset="0" yoffset="0" xadvance="7" page="0" chnl="0" letter="ť"/>
        <char id="358" x="799" y="73" width="10" height="20" xoffset="0" yoffset="0" xadvance="10" page="0" chnl="0" letter="Ŧ"/>
        <char id="359" x="813" y="73" width="7" height="20" xoffset="0" yoffset="0" xadvance="7" page="0" chnl="0" letter="ŧ"/>
        <char id="360" x="824" y="73" width="12" height="20" xoffset="0" yoffset="0" xadvance="12" page="0" chnl="0" letter="Ũ"/>
        <char id="361" x="840" y="73" width="10" height="20" xoffset="0" yoffset="0" xadvance="10" page="0" chnl="0" letter="ũ"/>
        <char id="362" x="854" y="73" width="12" height="20" xoffset="0" yoffset="0" xadvance="12" page="0" chnl="0" letter="Ū"/>
        <char id="363" x="870" y="73" width="10" height="20" xoffset="0" yoffset="0" xadvance="10" page="0" chnl="0" letter="ū"/>
        <char id="364" x="884" y="73" width="12" height="20" xoffset="0" yoffset="0" xadvance="12" page="0" chnl="0" letter="Ŭ"/>
        <char id="365" x="900" y="73" width="10" height="20" xoffset="0" yoffset="0" xadvance="10" page="0" chnl="0" letter="ŭ"/>
        <char id="366" x="914" y="73" width="12" height="20" xoffset="0" yoffset="0" xadvance="12" page="0" chnl="0" letter="Ů"/>
        <char id="367" x="930" y="73" width="10" height="20" xoffset="0" yoffset="0" xadvance="10" page="0" chnl="0" letter="ů"/>
        <char id="368" x="944" y="73" width="12" height="20" xoffset="0" yoffset="0" xadvance="12" page="0" chnl="0" letter="Ű"/>
        <char id="369" x="960" y="73" width="10" height="20" xoffset="0" yoffset="0" xadvance="10" page="0" chnl="0" letter="ű"/>
        <char id="370" x="974" y="73" width="12" height="20" xoffset="0" yoffset="0" xadvance="12" page="0" chnl="0" letter="Ų"/>
        <char id="371" x="990" y="73" width="10" height="20" xoffset="0" yoffset="0" xadvance="10" page="0" chnl="0" letter="ų"/>
        <char id="372" x="1004" y="73" width="15" height="20" xoffset="0" yoffset="0" xadvance="15" page="0" chnl="0" letter="Ŵ"/>
        <char id="373" x="1" y="97" width="14" height="20" xoffset="0" yoffset="0" xadvance="14" page="0" chnl="0" letter="ŵ"/>
        <char id="374" x="19" y="97" width="11" height="20" xoffset="0" yoffset="0" xadvance="11" page="0" chnl="0" letter="Ŷ"/>
        <char id="375" x="34" y="97" width="9" height="20" xoffset="0" yoffset="0" xadvance="9" page="0" chnl="0" letter="ŷ"/>
        <char id="376" x="47" y="97" width="11" height="20" xoffset="0" yoffset="0" xadvance="11" page="0" chnl="0" letter="Ÿ"/>
        <char id="377" x="62" y="97" width="9" height="20" xoffset="0" yoffset="0" xadvance="9" page="0" chnl="0" letter="Ź"/>
        <char id="378" x="75" y="97" width="9" height="20" xoffset="0" yoffset="0" xadvance="9" page="0" chnl="0" letter="ź"/>
        <char id="379" x="88" y="97" width="9" height="20" xoffset="0" yoffset="0" xadvance="9" page="0" chnl="0" letter="Ż"/>
        <char id="380" x="101" y="97" width="9" height="20" xoffset="0" yoffset="0" xadvance="9" page="0" chnl="0" letter="ż"/>
        <char id="381" x="114" y="97" width="9" height="20" xoffset="0" yoffset="0" xadvance="9" page="0" chnl="0" letter="Ž"/>
        <char id="382" x="127" y="97" width="9" height="20" xoffset="0" yoffset="0" xadvance="9" page="0" chnl="0" letter="ž"/>
        <char id="399" x="140" y="97" width="12" height="20" xoffset="0" yoffset="0" xadvance="12" page="0" chnl="0" letter="Ə"/>
        <char id="400" x="683" y="241" width="7" height="20" xoffset="0" yoffset="0" xadvance="7" page="0" chnl="0" letter="Ɛ"/>
        <char id="401" x="683" y="241" width="7" height="20" xoffset="0" yoffset="0" xadvance="7" page="0" chnl="0" letter="Ƒ"/>
        <char id="402" x="156" y="97" width="9" height="20" xoffset="0" yoffset="0" xadvance="9" page="0" chnl="0" letter="ƒ"/>
        <char id="439" x="169" y="97" width="10" height="20" xoffset="0" yoffset="0" xadvance="10" page="0" chnl="0" letter="Ʒ"/>
        <char id="461" x="183" y="97" width="11" height="20" xoffset="0" yoffset="0" xadvance="11" page="0" chnl="0" letter="Ǎ"/>
        <char id="462" x="198" y="97" width="10" height="20" xoffset="0" yoffset="0" xadvance="10" page="0" chnl="0" letter="ǎ"/>
        <char id="484" x="212" y="97" width="13" height="20" xoffset="0" yoffset="0" xadvance="13" page="0" chnl="0" letter="Ǥ"/>
        <char id="485" x="229" y="97" width="11" height="20" xoffset="0" yoffset="0" xadvance="11" page="0" chnl="0" letter="ǥ"/>
        <char id="486" x="244" y="97" width="12" height="20" xoffset="0" yoffset="0" xadvance="12" page="0" chnl="0" letter="Ǧ"/>
        <char id="487" x="260" y="97" width="10" height="20" xoffset="0" yoffset="0" xadvance="10" page="0" chnl="0" letter="ǧ"/>
        <char id="488" x="274" y="97" width="11" height="20" xoffset="0" yoffset="0" xadvance="11" page="0" chnl="0" letter="Ǩ"/>
        <char id="489" x="289" y="97" width="10" height="20" xoffset="0" yoffset="0" xadvance="10" page="0" chnl="0" letter="ǩ"/>
        <char id="494" x="303" y="97" width="10" height="20" xoffset="0" yoffset="0" xadvance="10" page="0" chnl="0" letter="Ǯ"/>
        <char id="495" x="317" y="97" width="10" height="20" xoffset="0" yoffset="0" xadvance="10" page="0" chnl="0" letter="ǯ"/>
        <char id="536" x="331" y="97" width="11" height="20" xoffset="0" yoffset="0" xadvance="11" page="0" chnl="0" letter="Ș"/>
        <char id="537" x="346" y="97" width="9" height="20" xoffset="0" yoffset="0" xadvance="9" page="0" chnl="0" letter="ș"/>
        <char id="538" x="359" y="97" width="10" height="20" xoffset="0" yoffset="0" xadvance="10" page="0" chnl="0" letter="Ț"/>
        <char id="539" x="373" y="97" width="7" height="20" xoffset="0" yoffset="0" xadvance="7" page="0" chnl="0" letter="ț"/>
        <char id="567" x="384" y="97" width="5" height="20" xoffset="0" yoffset="0" xadvance="5" page="0" chnl="0" letter="ȷ"/>
        <char id="601" x="393" y="97" width="10" height="20" xoffset="0" yoffset="0" xadvance="10" page="0" chnl="0" letter="ə"/>
        <char id="658" x="407" y="97" width="10" height="20" xoffset="0" yoffset="0" xadvance="10" page="0" chnl="0" letter="ʒ"/>
        <char id="697" x="421" y="97" width="4" height="20" xoffset="0" yoffset="0" xadvance="4" page="0" chnl="0" letter="ʹ"/>
        <char id="698" x="683" y="241" width="7" height="20" xoffset="0" yoffset="0" xadvance="7" page="0" chnl="0" letter="ʺ"/>
        <char id="699" x="683" y="241" width="7" height="20" xoffset="0" yoffset="0" xadvance="7" page="0" chnl="0" letter="ʻ"/>
        <char id="700" x="429" y="97" width="4" height="20" xoffset="0" yoffset="0" xadvance="4" page="0" chnl="0" letter="ʼ"/>
        <char id="710" x="437" y="97" width="6" height="20" xoffset="0" yoffset="0" xadvance="6" page="0" chnl="0" letter="ˆ"/>
        <char id="711" x="447" y="97" width="6" height="20" xoffset="0" yoffset="0" xadvance="6" page="0" chnl="0" letter="ˇ"/>
        <char id="712" x="457" y="97" width="3" height="20" xoffset="0" yoffset="0" xadvance="3" page="0" chnl="0" letter="ˈ"/>
        <char id="728" x="464" y="97" width="7" height="20" xoffset="0" yoffset="0" xadvance="7" page="0" chnl="0" letter="˘"/>
        <char id="729" x="475" y="97" width="3" height="20" xoffset="0" yoffset="0" xadvance="3" page="0" chnl="0" letter="˙"/>
        <char id="730" x="482" y="97" width="5" height="20" xoffset="0" yoffset="0" xadvance="5" page="0" chnl="0" letter="˚"/>
        <char id="731" x="491" y="97" width="5" height="20" xoffset="0" yoffset="0" xadvance="5" page="0" chnl="0" letter="˛"/>
        <char id="732" x="500" y="97" width="7" height="20" xoffset="0" yoffset="0" xadvance="7" page="0" chnl="0" letter="˜"/>
        <char id="733" x="511" y="97" width="6" height="20" xoffset="0" yoffset="0" xadvance="6" page="0" chnl="0" letter="˝"/>
        <char id="768" x="521" y="97" width="0" height="20" xoffset="0" yoffset="0" xadvance="0" page="0" chnl="0" letter="̀"/>
        <char id="769" x="525" y="97" width="0" height="20" xoffset="0" yoffset="0" xadvance="0" page="0" chnl="0" letter="́"/>
        <char id="770" x="529" y="97" width="0" height="20" xoffset="0" yoffset="0" xadvance="0" page="0" chnl="0" letter="̂"/>
        <char id="771" x="533" y="97" width="0" height="20" xoffset="0" yoffset="0" xadvance="0" page="0" chnl="0" letter="̃"/>
        <char id="772" x="537" y="97" width="0" height="20" xoffset="0" yoffset="0" xadvance="0" page="0" chnl="0" letter="̄"/>
        <char id="774" x="541" y="97" width="0" height="20" xoffset="0" yoffset="0" xadvance="0" page="0" chnl="0" letter="̆"/>
        <char id="775" x="545" y="97" width="0" height="20" xoffset="0" yoffset="0" xadvance="0" page="0" chnl="0" letter="̇"/>
        <char id="776" x="549" y="97" width="0" height="20" xoffset="0" yoffset="0" xadvance="0" page="0" chnl="0" letter="̈"/>
        <char id="777" x="683" y="241" width="7" height="20" xoffset="0" yoffset="0" xadvance="7" page="0" chnl="0" letter="̉"/>
        <char id="778" x="553" y="97" width="0" height="20" xoffset="0" yoffset="0" xadvance="0" page="0" chnl="0" letter="̊"/>
        <char id="779" x="557" y="97" width="0" height="20" xoffset="0" yoffset="0" xadvance="0" page="0" chnl="0" letter="̋"/>
        <char id="780" x="561" y="97" width="0" height="20" xoffset="0" yoffset="0" xadvance="0" page="0" chnl="0" letter="̌"/>
        <char id="786" x="565" y="97" width="0" height="20" xoffset="0" yoffset="0" xadvance="0" page="0" chnl="0" letter="̒"/>
        <char id="806" x="569" y="97" width="0" height="20" xoffset="0" yoffset="0" xadvance="0" page="0" chnl="0" letter="̦"/>
        <char id="807" x="573" y="97" width="0" height="20" xoffset="0" yoffset="0" xadvance="0" page="0" chnl="0" letter="̧"/>
        <char id="808" x="577" y="97" width="0" height="20" xoffset="0" yoffset="0" xadvance="0" page="0" chnl="0" letter="̨"/>
        <char id="821" x="581" y="97" width="0" height="20" xoffset="0" yoffset="0" xadvance="0" page="0" chnl="0" letter="̵"/>
        <char id="923" x="585" y="97" width="11" height="20" xoffset="0" yoffset="0" xadvance="11" page="0" chnl="0" letter="Λ"/>
        <char id="937" x="600" y="97" width="12" height="20" xoffset="0" yoffset="0" xadvance="12" page="0" chnl="0" letter="Ω"/>
        <char id="955" x="616" y="97" width="10" height="20" xoffset="0" yoffset="0" xadvance="10" page="0" chnl="0" letter="λ"/>
        <char id="960" x="630" y="97" width="11" height="20" xoffset="0" yoffset="0" xadvance="11" page="0" chnl="0" letter="π"/>
        <char id="1024" x="645" y="97" width="10" height="20" xoffset="0" yoffset="0" xadvance="10" page="0" chnl="0" letter="Ѐ"/>
        <char id="1025" x="659" y="97" width="10" height="20" xoffset="0" yoffset="0" xadvance="10" page="0" chnl="0" letter="Ё"/>
        <char id="1026" x="673" y="97" width="13" height="20" xoffset="0" yoffset="0" xadvance="13" page="0" chnl="0" letter="Ђ"/>
        <char id="1027" x="690" y="97" width="10" height="20" xoffset="0" yoffset="0" xadvance="10" page="0" chnl="0" letter="Ѓ"/>
        <char id="1028" x="704" y="97" width="12" height="20" xoffset="0" yoffset="0" xadvance="12" page="0" chnl="0" letter="Є"/>
        <char id="1029" x="720" y="97" width="11" height="20" xoffset="0" yoffset="0" xadvance="11" page="0" chnl="0" letter="Ѕ"/>
        <char id="1030" x="735" y="97" width="5" height="20" xoffset="0" yoffset="0" xadvance="5" page="0" chnl="0" letter="І"/>
        <char id="1031" x="744" y="97" width="5" height="20" xoffset="0" yoffset="0" xadvance="5" page="0" chnl="0" letter="Ї"/>
        <char id="1032" x="753" y="97" width="10" height="20" xoffset="0" yoffset="0" xadvance="10" page="0" chnl="0" letter="Ј"/>
        <char id="1033" x="767" y="97" width="19" height="20" xoffset="0" yoffset="0" xadvance="19" page="0" chnl="0" letter="Љ"/>
        <char id="1034" x="790" y="97" width="18" height="20" xoffset="0" yoffset="0" xadvance="18" page="0" chnl="0" letter="Њ"/>
        <char id="1035" x="812" y="97" width="13" height="20" xoffset="0" yoffset="0" xadvance="13" page="0" chnl="0" letter="Ћ"/>
        <char id="1036" x="829" y="97" width="11" height="20" xoffset="0" yoffset="0" xadvance="11" page="0" chnl="0" letter="Ќ"/>
        <char id="1038" x="844" y="97" width="9" height="20" xoffset="0" yoffset="0" xadvance="9" page="0" chnl="0" letter="Ў"/>
        <char id="1039" x="857" y="97" width="12" height="20" xoffset="0" yoffset="0" xadvance="12" page="0" chnl="0" letter="Џ"/>
        <char id="1040" x="873" y="97" width="11" height="20" xoffset="0" yoffset="0" xadvance="11" page="0" chnl="0" letter="А"/>
        <char id="1041" x="888" y="97" width="11" height="20" xoffset="0" yoffset="0" xadvance="11" page="0" chnl="0" letter="Б"/>
        <char id="1042" x="903" y="97" width="11" height="20" xoffset="0" yoffset="0" xadvance="11" page="0" chnl="0" letter="В"/>
        <char id="1043" x="918" y="97" width="10" height="20" xoffset="0" yoffset="0" xadvance="10" page="0" chnl="0" letter="Г"/>
        <char id="1044" x="932" y="97" width="13" height="20" xoffset="0" yoffset="0" xadvance="13" page="0" chnl="0" letter="Д"/>
        <char id="1045" x="949" y="97" width="10" height="20" xoffset="0" yoffset="0" xadvance="10" page="0" chnl="0" letter="Е"/>
        <char id="1046" x="963" y="97" width="16" height="20" xoffset="0" yoffset="0" xadvance="16" page="0" chnl="0" letter="Ж"/>
        <char id="1047" x="983" y="97" width="11" height="20" xoffset="0" yoffset="0" xadvance="11" page="0" chnl="0" letter="З"/>
        <char id="1048" x="998" y="97" width="12" height="20" xoffset="0" yoffset="0" xadvance="12" page="0" chnl="0" letter="И"/>
        <char id="1049" x="1" y="121" width="12" height="20" xoffset="0" yoffset="0" xadvance="12" page="0" chnl="0" letter="Й"/>
        <char id="1050" x="17" y="121" width="11" height="20" xoffset="0" yoffset="0" xadvance="11" page="0" chnl="0" letter="К"/>
        <char id="1051" x="32" y="121" width="13" height="20" xoffset="0" yoffset="0" xadvance="13" page="0" chnl="0" letter="Л"/>
        <char id="1052" x="49" y="121" width="15" height="20" xoffset="0" yoffset="0" xadvance="15" page="0" chnl="0" letter="М"/>
        <char id="1053" x="68" y="121" width="12" height="20" xoffset="0" yoffset="0" xadvance="12" page="0" chnl="0" letter="Н"/>
        <char id="1054" x="84" y="121" width="12" height="20" xoffset="0" yoffset="0" xadvance="12" page="0" chnl="0" letter="О"/>
        <char id="1055" x="100" y="121" width="12" height="20" xoffset="0" yoffset="0" xadvance="12" page="0" chnl="0" letter="П"/>
        <char id="1056" x="116" y="121" width="11" height="20" xoffset="0" yoffset="0" xadvance="11" page="0" chnl="0" letter="Р"/>
        <char id="1057" x="131" y="121" width="12" height="20" xoffset="0" yoffset="0" xadvance="12" page="0" chnl="0" letter="С"/>
        <char id="1058" x="147" y="121" width="10" height="20" xoffset="0" yoffset="0" xadvance="10" page="0" chnl="0" letter="Т"/>
        <char id="1059" x="161" y="121" width="9" height="20" xoffset="0" yoffset="0" xadvance="9" page="0" chnl="0" letter="У"/>
        <char id="1060" x="174" y="121" width="14" height="20" xoffset="0" yoffset="0" xadvance="14" page="0" chnl="0" letter="Ф"/>
        <char id="1061" x="192" y="121" width="11" height="20" xoffset="0" yoffset="0" xadvance="11" page="0" chnl="0" letter="Х"/>
        <char id="1062" x="207" y="121" width="13" height="20" xoffset="0" yoffset="0" xadvance="13" page="0" chnl="0" letter="Ц"/>
        <char id="1063" x="224" y="121" width="11" height="20" xoffset="0" yoffset="0" xadvance="11" page="0" chnl="0" letter="Ч"/>
        <char id="1064" x="239" y="121" width="15" height="20" xoffset="0" yoffset="0" xadvance="15" page="0" chnl="0" letter="Ш"/>
        <char id="1065" x="258" y="121" width="16" height="20" xoffset="0" yoffset="0" xadvance="16" page="0" chnl="0" letter="Щ"/>
        <char id="1066" x="278" y="121" width="12" height="20" xoffset="0" yoffset="0" xadvance="12" page="0" chnl="0" letter="Ъ"/>
        <char id="1067" x="294" y="121" width="14" height="20" xoffset="0" yoffset="0" xadvance="14" page="0" chnl="0" letter="Ы"/>
        <char id="1068" x="312" y="121" width="11" height="20" xoffset="0" yoffset="0" xadvance="11" page="0" chnl="0" letter="Ь"/>
        <char id="1069" x="327" y="121" width="12" height="20" xoffset="0" yoffset="0" xadvance="12" page="0" chnl="0" letter="Э"/>
        <char id="1070" x="343" y="121" width="16" height="20" xoffset="0" yoffset="0" xadvance="16" page="0" chnl="0" letter="Ю"/>
        <char id="1071" x="363" y="121" width="11" height="20" xoffset="0" yoffset="0" xadvance="11" page="0" chnl="0" letter="Я"/>
        <char id="1072" x="378" y="121" width="10" height="20" xoffset="0" yoffset="0" xadvance="10" page="0" chnl="0" letter="а"/>
        <char id="1073" x="392" y="121" width="10" height="20" xoffset="0" yoffset="0" xadvance="10" page="0" chnl="0" letter="б"/>
        <char id="1074" x="406" y="121" width="10" height="20" xoffset="0" yoffset="0" xadvance="10" page="0" chnl="0" letter="в"/>
        <char id="1075" x="420" y="121" width="8" height="20" xoffset="0" yoffset="0" xadvance="8" page="0" chnl="0" letter="г"/>
        <char id="1076" x="432" y="121" width="12" height="20" xoffset="0" yoffset="0" xadvance="12" page="0" chnl="0" letter="д"/>
        <char id="1077" x="448" y="121" width="10" height="20" xoffset="0" yoffset="0" xadvance="10" page="0" chnl="0" letter="е"/>
        <char id="1078" x="462" y="121" width="14" height="20" xoffset="0" yoffset="0" xadvance="14" page="0" chnl="0" letter="ж"/>
        <char id="1079" x="480" y="121" width="9" height="20" xoffset="0" yoffset="0" xadvance="9" page="0" chnl="0" letter="з"/>
        <char id="1080" x="493" y="121" width="10" height="20" xoffset="0" yoffset="0" xadvance="10" page="0" chnl="0" letter="и"/>
        <char id="1081" x="507" y="121" width="10" height="20" xoffset="0" yoffset="0" xadvance="10" page="0" chnl="0" letter="й"/>
        <char id="1082" x="521" y="121" width="10" height="20" xoffset="0" yoffset="0" xadvance="10" page="0" chnl="0" letter="к"/>
        <char id="1083" x="535" y="121" width="11" height="20" xoffset="0" yoffset="0" xadvance="11" page="0" chnl="0" letter="л"/>
        <char id="1084" x="550" y="121" width="12" height="20" xoffset="0" yoffset="0" xadvance="12" page="0" chnl="0" letter="м"/>
        <char id="1085" x="566" y="121" width="10" height="20" xoffset="0" yoffset="0" xadvance="10" page="0" chnl="0" letter="н"/>
        <char id="1086" x="580" y="121" width="10" height="20" xoffset="0" yoffset="0" xadvance="10" page="0" chnl="0" letter="о"/>
        <char id="1087" x="594" y="121" width="10" height="20" xoffset="0" yoffset="0" xadvance="10" page="0" chnl="0" letter="п"/>
        <char id="1088" x="608" y="121" width="10" height="20" xoffset="0" yoffset="0" xadvance="10" page="0" chnl="0" letter="р"/>
        <char id="1089" x="622" y="121" width="9" height="20" xoffset="0" yoffset="0" xadvance="9" page="0" chnl="0" letter="с"/>
        <char id="1090" x="635" y="121" width="9" height="20" xoffset="0" yoffset="0" xadvance="9" page="0" chnl="0" letter="т"/>
        <char id="1091" x="648" y="121" width="9" height="20" xoffset="0" yoffset="0" xadvance="9" page="0" chnl="0" letter="у"/>
        <char id="1092" x="661" y="121" width="11" height="20" xoffset="0" yoffset="0" xadvance="11" page="0" chnl="0" letter="ф"/>
        <char id="1093" x="676" y="121" width="10" height="20" xoffset="0" yoffset="0" xadvance="10" page="0" chnl="0" letter="х"/>
        <char id="1094" x="690" y="121" width="11" height="20" xoffset="0" yoffset="0" xadvance="11" page="0" chnl="0" letter="ц"/>
        <char id="1095" x="705" y="121" width="10" height="20" xoffset="0" yoffset="0" xadvance="10" page="0" chnl="0" letter="ч"/>
        <char id="1096" x="719" y="121" width="13" height="20" xoffset="0" yoffset="0" xadvance="13" page="0" chnl="0" letter="ш"/>
        <char id="1097" x="736" y="121" width="14" height="20" xoffset="0" yoffset="0" xadvance="14" page="0" chnl="0" letter="щ"/>
        <char id="1098" x="754" y="121" width="11" height="20" xoffset="0" yoffset="0" xadvance="11" page="0" chnl="0" letter="ъ"/>
        <char id="1099" x="769" y="121" width="13" height="20" xoffset="0" yoffset="0" xadvance="13" page="0" chnl="0" letter="ы"/>
        <char id="1100" x="786" y="121" width="10" height="20" xoffset="0" yoffset="0" xadvance="10" page="0" chnl="0" letter="ь"/>
        <char id="1101" x="800" y="121" width="10" height="20" xoffset="0" yoffset="0" xadvance="10" page="0" chnl="0" letter="э"/>
        <char id="1102" x="814" y="121" width="13" height="20" xoffset="0" yoffset="0" xadvance="13" page="0" chnl="0" letter="ю"/>
        <char id="1103" x="831" y="121" width="10" height="20" xoffset="0" yoffset="0" xadvance="10" page="0" chnl="0" letter="я"/>
        <char id="1104" x="845" y="121" width="10" height="20" xoffset="0" yoffset="0" xadvance="10" page="0" chnl="0" letter="ѐ"/>
        <char id="1105" x="859" y="121" width="10" height="20" xoffset="0" yoffset="0" xadvance="10" page="0" chnl="0" letter="ё"/>
        <char id="1106" x="873" y="121" width="10" height="20" xoffset="0" yoffset="0" xadvance="10" page="0" chnl="0" letter="ђ"/>
        <char id="1107" x="887" y="121" width="8" height="20" xoffset="0" yoffset="0" xadvance="8" page="0" chnl="0" letter="ѓ"/>
        <char id="1108" x="899" y="121" width="10" height="20" xoffset="0" yoffset="0" xadvance="10" page="0" chnl="0" letter="є"/>
        <char id="1109" x="913" y="121" width="9" height="20" xoffset="0" yoffset="0" xadvance="9" page="0" chnl="0" letter="ѕ"/>
        <char id="1110" x="926" y="121" width="4" height="20" xoffset="0" yoffset="0" xadvance="4" page="0" chnl="0" letter="і"/>
        <char id="1111" x="934" y="121" width="4" height="20" xoffset="0" yoffset="0" xadvance="4" page="0" chnl="0" letter="ї"/>
        <char id="1112" x="942" y="121" width="5" height="20" xoffset="0" yoffset="0" xadvance="5" page="0" chnl="0" letter="ј"/>
        <char id="1113" x="951" y="121" width="17" height="20" xoffset="0" yoffset="0" xadvance="17" page="0" chnl="0" letter="љ"/>
        <char id="1114" x="972" y="121" width="15" height="20" xoffset="0" yoffset="0" xadvance="15" page="0" chnl="0" letter="њ"/>
        <char id="1115" x="991" y="121" width="10" height="20" xoffset="0" yoffset="0" xadvance="10" page="0" chnl="0" letter="ћ"/>
        <char id="1116" x="1005" y="121" width="10" height="20" xoffset="0" yoffset="0" xadvance="10" page="0" chnl="0" letter="ќ"/>
        <char id="1117" x="1" y="145" width="10" height="20" xoffset="0" yoffset="0" xadvance="10" page="0" chnl="0" letter="ѝ"/>
        <char id="1118" x="15" y="145" width="9" height="20" xoffset="0" yoffset="0" xadvance="9" page="0" chnl="0" letter="ў"/>
        <char id="1119" x="28" y="145" width="10" height="20" xoffset="0" yoffset="0" xadvance="10" page="0" chnl="0" letter="џ"/>
        <char id="1122" x="42" y="145" width="12" height="20" xoffset="0" yoffset="0" xadvance="12" page="0" chnl="0" letter="Ѣ"/>
        <char id="1123" x="58" y="145" width="11" height="20" xoffset="0" yoffset="0" xadvance="11" page="0" chnl="0" letter="ѣ"/>
        <char id="1130" x="73" y="145" width="12" height="20" xoffset="0" yoffset="0" xadvance="12" page="0" chnl="0" letter="Ѫ"/>
        <char id="1131" x="89" y="145" width="12" height="20" xoffset="0" yoffset="0" xadvance="12" page="0" chnl="0" letter="ѫ"/>
        <char id="1138" x="105" y="145" width="12" height="20" xoffset="0" yoffset="0" xadvance="12" page="0" chnl="0" letter="Ѳ"/>
        <char id="1139" x="121" y="145" width="10" height="20" xoffset="0" yoffset="0" xadvance="10" page="0" chnl="0" letter="ѳ"/>
        <char id="1140" x="135" y="145" width="12" height="20" xoffset="0" yoffset="0" xadvance="12" page="0" chnl="0" letter="Ѵ"/>
        <char id="1141" x="151" y="145" width="10" height="20" xoffset="0" yoffset="0" xadvance="10" page="0" chnl="0" letter="ѵ"/>
        <char id="1168" x="165" y="145" width="9" height="20" xoffset="0" yoffset="0" xadvance="9" page="0" chnl="0" letter="Ґ"/>
        <char id="1169" x="178" y="145" width="7" height="20" xoffset="0" yoffset="0" xadvance="7" page="0" chnl="0" letter="ґ"/>
        <char id="1170" x="189" y="145" width="11" height="20" xoffset="0" yoffset="0" xadvance="11" page="0" chnl="0" letter="Ғ"/>
        <char id="1171" x="204" y="145" width="9" height="20" xoffset="0" yoffset="0" xadvance="9" page="0" chnl="0" letter="ғ"/>
        <char id="1172" x="683" y="241" width="7" height="20" xoffset="0" yoffset="0" xadvance="7" page="0" chnl="0" letter="Ҕ"/>
        <char id="1173" x="683" y="241" width="7" height="20" xoffset="0" yoffset="0" xadvance="7" page="0" chnl="0" letter="ҕ"/>
        <char id="1174" x="217" y="145" width="16" height="20" xoffset="0" yoffset="0" xadvance="16" page="0" chnl="0" letter="Җ"/>
        <char id="1175" x="237" y="145" width="14" height="20" xoffset="0" yoffset="0" xadvance="14" page="0" chnl="0" letter="җ"/>
        <char id="1176" x="683" y="241" width="7" height="20" xoffset="0" yoffset="0" xadvance="7" page="0" chnl="0" letter="Ҙ"/>
        <char id="1177" x="683" y="241" width="7" height="20" xoffset="0" yoffset="0" xadvance="7" page="0" chnl="0" letter="ҙ"/>
        <char id="1178" x="255" y="145" width="11" height="20" xoffset="0" yoffset="0" xadvance="11" page="0" chnl="0" letter="Қ"/>
        <char id="1179" x="270" y="145" width="10" height="20" xoffset="0" yoffset="0" xadvance="10" page="0" chnl="0" letter="қ"/>
        <char id="1186" x="284" y="145" width="12" height="20" xoffset="0" yoffset="0" xadvance="12" page="0" chnl="0" letter="Ң"/>
        <char id="1187" x="300" y="145" width="11" height="20" xoffset="0" yoffset="0" xadvance="11" page="0" chnl="0" letter="ң"/>
        <char id="1198" x="315" y="145" width="11" height="20" xoffset="0" yoffset="0" xadvance="11" page="0" chnl="0" letter="Ү"/>
        <char id="1199" x="330" y="145" width="9" height="20" xoffset="0" yoffset="0" xadvance="9" page="0" chnl="0" letter="ү"/>
        <char id="1200" x="343" y="145" width="11" height="20" xoffset="0" yoffset="0" xadvance="11" page="0" chnl="0" letter="Ұ"/>
        <char id="1201" x="358" y="145" width="9" height="20" xoffset="0" yoffset="0" xadvance="9" page="0" chnl="0" letter="ұ"/>
        <char id="1202" x="371" y="145" width="11" height="20" xoffset="0" yoffset="0" xadvance="11" page="0" chnl="0" letter="Ҳ"/>
        <char id="1203" x="386" y="145" width="10" height="20" xoffset="0" yoffset="0" xadvance="10" page="0" chnl="0" letter="ҳ"/>
        <char id="1206" x="400" y="145" width="12" height="20" xoffset="0" yoffset="0" xadvance="12" page="0" chnl="0" letter="Ҷ"/>
        <char id="1207" x="416" y="145" width="11" height="20" xoffset="0" yoffset="0" xadvance="11" page="0" chnl="0" letter="ҷ"/>
        <char id="1208" x="683" y="241" width="7" height="20" xoffset="0" yoffset="0" xadvance="7" page="0" chnl="0" letter="Ҹ"/>
        <char id="1209" x="683" y="241" width="7" height="20" xoffset="0" yoffset="0" xadvance="7" page="0" chnl="0" letter="ҹ"/>
        <char id="1210" x="431" y="145" width="11" height="20" xoffset="0" yoffset="0" xadvance="11" page="0" chnl="0" letter="Һ"/>
        <char id="1211" x="446" y="145" width="10" height="20" xoffset="0" yoffset="0" xadvance="10" page="0" chnl="0" letter="һ"/>
        <char id="1216" x="460" y="145" width="5" height="20" xoffset="0" yoffset="0" xadvance="5" page="0" chnl="0" letter="Ӏ"/>
        <char id="1231" x="469" y="145" width="5" height="20" xoffset="0" yoffset="0" xadvance="5" page="0" chnl="0" letter="ӏ"/>
        <char id="1240" x="478" y="145" width="12" height="20" xoffset="0" yoffset="0" xadvance="12" page="0" chnl="0" letter="Ә"/>
        <char id="1241" x="494" y="145" width="10" height="20" xoffset="0" yoffset="0" xadvance="10" page="0" chnl="0" letter="ә"/>
        <char id="1250" x="508" y="145" width="12" height="20" xoffset="0" yoffset="0" xadvance="12" page="0" chnl="0" letter="Ӣ"/>
        <char id="1251" x="524" y="145" width="10" height="20" xoffset="0" yoffset="0" xadvance="10" page="0" chnl="0" letter="ӣ"/>
        <char id="1256" x="538" y="145" width="12" height="20" xoffset="0" yoffset="0" xadvance="12" page="0" chnl="0" letter="Ө"/>
        <char id="1257" x="554" y="145" width="10" height="20" xoffset="0" yoffset="0" xadvance="10" page="0" chnl="0" letter="ө"/>
        <char id="1262" x="568" y="145" width="9" height="20" xoffset="0" yoffset="0" xadvance="9" page="0" chnl="0" letter="Ӯ"/>
        <char id="1263" x="581" y="145" width="9" height="20" xoffset="0" yoffset="0" xadvance="9" page="0" chnl="0" letter="ӯ"/>
        <char id="3647" x="594" y="145" width="11" height="20" xoffset="0" yoffset="0" xadvance="11" page="0" chnl="0" letter="฿"/>
        <char id="7712" x="609" y="145" width="12" height="20" xoffset="0" yoffset="0" xadvance="12" page="0" chnl="0" letter="Ḡ"/>
        <char id="7713" x="625" y="145" width="10" height="20" xoffset="0" yoffset="0" xadvance="10" page="0" chnl="0" letter="ḡ"/>
        <char id="7808" x="639" y="145" width="15" height="20" xoffset="0" yoffset="0" xadvance="15" page="0" chnl="0" letter="Ẁ"/>
        <char id="7809" x="658" y="145" width="14" height="20" xoffset="0" yoffset="0" xadvance="14" page="0" chnl="0" letter="ẁ"/>
        <char id="7810" x="676" y="145" width="15" height="20" xoffset="0" yoffset="0" xadvance="15" page="0" chnl="0" letter="Ẃ"/>
        <char id="7811" x="695" y="145" width="14" height="20" xoffset="0" yoffset="0" xadvance="14" page="0" chnl="0" letter="ẃ"/>
        <char id="7812" x="713" y="145" width="15" height="20" xoffset="0" yoffset="0" xadvance="15" page="0" chnl="0" letter="Ẅ"/>
        <char id="7813" x="732" y="145" width="14" height="20" xoffset="0" yoffset="0" xadvance="14" page="0" chnl="0" letter="ẅ"/>
        <char id="7838" x="750" y="145" width="12" height="20" xoffset="0" yoffset="0" xadvance="12" page="0" chnl="0" letter="ẞ"/>
        <char id="7868" x="766" y="145" width="10" height="20" xoffset="0" yoffset="0" xadvance="10" page="0" chnl="0" letter="Ẽ"/>
        <char id="7869" x="780" y="145" width="10" height="20" xoffset="0" yoffset="0" xadvance="10" page="0" chnl="0" letter="ẽ"/>
        <char id="7922" x="794" y="145" width="11" height="20" xoffset="0" yoffset="0" xadvance="11" page="0" chnl="0" letter="Ỳ"/>
        <char id="7923" x="809" y="145" width="9" height="20" xoffset="0" yoffset="0" xadvance="9" page="0" chnl="0" letter="ỳ"/>
        <char id="7928" x="822" y="145" width="11" height="20" xoffset="0" yoffset="0" xadvance="11" page="0" chnl="0" letter="Ỹ"/>
        <char id="7929" x="837" y="145" width="9" height="20" xoffset="0" yoffset="0" xadvance="9" page="0" chnl="0" letter="ỹ"/>
        <char id="8211" x="850" y="145" width="10" height="20" xoffset="0" yoffset="0" xadvance="10" page="0" chnl="0" letter="–"/>
        <char id="8212" x="864" y="145" width="15" height="20" xoffset="0" yoffset="0" xadvance="15" page="0" chnl="0" letter="—"/>
        <char id="8213" x="683" y="241" width="7" height="20" xoffset="0" yoffset="0" xadvance="7" page="0" chnl="0" letter="―"/>
        <char id="8214" x="683" y="241" width="7" height="20" xoffset="0" yoffset="0" xadvance="7" page="0" chnl="0" letter="‖"/>
        <char id="8215" x="683" y="241" width="7" height="20" xoffset="0" yoffset="0" xadvance="7" page="0" chnl="0" letter="‗"/>
        <char id="8216" x="883" y="145" width="4" height="20" xoffset="0" yoffset="0" xadvance="4" page="0" chnl="0" letter="‘"/>
        <char id="8217" x="891" y="145" width="4" height="20" xoffset="0" yoffset="0" xadvance="4" page="0" chnl="0" letter="’"/>
        <char id="8218" x="899" y="145" width="4" height="20" xoffset="0" yoffset="0" xadvance="4" page="0" chnl="0" letter="‚"/>
        <char id="8219" x="683" y="241" width="7" height="20" xoffset="0" yoffset="0" xadvance="7" page="0" chnl="0" letter="‛"/>
        <char id="8220" x="907" y="145" width="6" height="20" xoffset="0" yoffset="0" xadvance="6" page="0" chnl="0" letter="“"/>
        <char id="8221" x="917" y="145" width="6" height="20" xoffset="0" yoffset="0" xadvance="6" page="0" chnl="0" letter="”"/>
        <char id="8222" x="927" y="145" width="6" height="20" xoffset="0" yoffset="0" xadvance="6" page="0" chnl="0" letter="„"/>
        <char id="8223" x="683" y="241" width="7" height="20" xoffset="0" yoffset="0" xadvance="7" page="0" chnl="0" letter="‟"/>
        <char id="8224" x="937" y="145" width="10" height="20" xoffset="0" yoffset="0" xadvance="10" page="0" chnl="0" letter="†"/>
        <char id="8225" x="951" y="145" width="10" height="20" xoffset="0" yoffset="0" xadvance="10" page="0" chnl="0" letter="‡"/>
        <char id="8226" x="965" y="145" width="5" height="20" xoffset="0" yoffset="0" xadvance="5" page="0" chnl="0" letter="•"/>
        <char id="8227" x="683" y="241" width="7" height="20" xoffset="0" yoffset="0" xadvance="7" page="0" chnl="0" letter="‣"/>
        <char id="8228" x="683" y="241" width="7" height="20" xoffset="0" yoffset="0" xadvance="7" page="0" chnl="0" letter="․"/>
        <char id="8229" x="683" y="241" width="7" height="20" xoffset="0" yoffset="0" xadvance="7" page="0" chnl="0" letter="‥"/>
        <char id="8230" x="974" y="145" width="10" height="20" xoffset="0" yoffset="0" xadvance="10" page="0" chnl="0" letter="…"/>
        <char id="8240" x="988" y="145" width="18" height="20" xoffset="0" yoffset="0" xadvance="18" page="0" chnl="0" letter="‰"/>
        <char id="8241" x="683" y="241" width="7" height="20" xoffset="0" yoffset="0" xadvance="7" page="0" chnl="0" letter="‱"/>
        <char id="8242" x="1010" y="145" width="4" height="20" xoffset="0" yoffset="0" xadvance="4" page="0" chnl="0" letter="′"/>
        <char id="8243" x="1018" y="145" width="6" height="20" xoffset="0" yoffset="0" xadvance="6" page="0" chnl="0" letter="″"/>
        <char id="8249" x="1" y="169" width="6" height="20" xoffset="0" yoffset="0" xadvance="6" page="0" chnl="0" letter="‹"/>
        <char id="8250" x="11" y="169" width="6" height="20" xoffset="0" yoffset="0" xadvance="6" page="0" chnl="0" letter="›"/>
        <char id="8260" x="21" y="169" width="10" height="20" xoffset="0" yoffset="0" xadvance="10" page="0" chnl="0" letter="⁄"/>
        <char id="8304" x="35" y="169" width="10" height="20" xoffset="0" yoffset="0" xadvance="10" page="0" chnl="0" letter="⁰"/>
        <char id="8308" x="49" y="169" width="10" height="20" xoffset="0" yoffset="0" xadvance="10" page="0" chnl="0" letter="⁴"/>
        <char id="8309" x="63" y="169" width="10" height="20" xoffset="0" yoffset="0" xadvance="10" page="0" chnl="0" letter="⁵"/>
        <char id="8310" x="77" y="169" width="10" height="20" xoffset="0" yoffset="0" xadvance="10" page="0" chnl="0" letter="⁶"/>
        <char id="8311" x="91" y="169" width="10" height="20" xoffset="0" yoffset="0" xadvance="10" page="0" chnl="0" letter="⁷"/>
        <char id="8312" x="105" y="169" width="10" height="20" xoffset="0" yoffset="0" xadvance="10" page="0" chnl="0" letter="⁸"/>
        <char id="8313" x="119" y="169" width="10" height="20" xoffset="0" yoffset="0" xadvance="10" page="0" chnl="0" letter="⁹"/>
        <char id="8320" x="133" y="169" width="10" height="20" xoffset="0" yoffset="0" xadvance="10" page="0" chnl="0" letter="₀"/>
        <char id="8321" x="147" y="169" width="10" height="20" xoffset="0" yoffset="0" xadvance="10" page="0" chnl="0" letter="₁"/>
        <char id="8322" x="161" y="169" width="10" height="20" xoffset="0" yoffset="0" xadvance="10" page="0" chnl="0" letter="₂"/>
        <char id="8323" x="175" y="169" width="10" height="20" xoffset="0" yoffset="0" xadvance="10" page="0" chnl="0" letter="₃"/>
        <char id="8324" x="189" y="169" width="10" height="20" xoffset="0" yoffset="0" xadvance="10" page="0" chnl="0" letter="₄"/>
        <char id="8325" x="203" y="169" width="10" height="20" xoffset="0" yoffset="0" xadvance="10" page="0" chnl="0" letter="₅"/>
        <char id="8326" x="217" y="169" width="10" height="20" xoffset="0" yoffset="0" xadvance="10" page="0" chnl="0" letter="₆"/>
        <char id="8327" x="231" y="169" width="10" height="20" xoffset="0" yoffset="0" xadvance="10" page="0" chnl="0" letter="₇"/>
        <char id="8328" x="245" y="169" width="10" height="20" xoffset="0" yoffset="0" xadvance="10" page="0" chnl="0" letter="₈"/>
        <char id="8329" x="259" y="169" width="10" height="20" xoffset="0" yoffset="0" xadvance="10" page="0" chnl="0" letter="₉"/>
        <char id="8362" x="273" y="169" width="13" height="20" xoffset="0" yoffset="0" xadvance="13" page="0" chnl="0" letter="₪"/>
        <char id="8363" x="683" y="241" width="7" height="20" xoffset="0" yoffset="0" xadvance="7" page="0" chnl="0" letter="₫"/>
        <char id="8364" x="290" y="169" width="12" height="20" xoffset="0" yoffset="0" xadvance="12" page="0" chnl="0" letter="€"/>
        <char id="8372" x="306" y="169" width="11" height="20" xoffset="0" yoffset="0" xadvance="11" page="0" chnl="0" letter="₴"/>
        <char id="8377" x="321" y="169" width="11" height="20" xoffset="0" yoffset="0" xadvance="11" page="0" chnl="0" letter="₹"/>
        <char id="8378" x="683" y="241" width="7" height="20" xoffset="0" yoffset="0" xadvance="7" page="0" chnl="0" letter="₺"/>
        <char id="8379" x="683" y="241" width="7" height="20" xoffset="0" yoffset="0" xadvance="7" page="0" chnl="0" letter="₻"/>
        <char id="8380" x="683" y="241" width="7" height="20" xoffset="0" yoffset="0" xadvance="7" page="0" chnl="0" letter="₼"/>
        <char id="8381" x="336" y="169" width="12" height="20" xoffset="0" yoffset="0" xadvance="12" page="0" chnl="0" letter="₽"/>
        <char id="8455" x="352" y="169" width="10" height="20" xoffset="0" yoffset="0" xadvance="10" page="0" chnl="0" letter="ℇ"/>
        <char id="8470" x="366" y="169" width="18" height="20" xoffset="0" yoffset="0" xadvance="18" page="0" chnl="0" letter="№"/>
        <char id="8471" x="388" y="169" width="10" height="20" xoffset="0" yoffset="0" xadvance="10" page="0" chnl="0" letter="℗"/>
        <char id="8482" x="402" y="169" width="15" height="20" xoffset="0" yoffset="0" xadvance="15" page="0" chnl="0" letter="™"/>
        <char id="8531" x="421" y="169" width="16" height="20" xoffset="0" yoffset="0" xadvance="16" page="0" chnl="0" letter="⅓"/>
        <char id="8532" x="441" y="169" width="16" height="20" xoffset="0" yoffset="0" xadvance="16" page="0" chnl="0" letter="⅔"/>
        <char id="8533" x="461" y="169" width="16" height="20" xoffset="0" yoffset="0" xadvance="16" page="0" chnl="0" letter="⅕"/>
        <char id="8539" x="481" y="169" width="16" height="20" xoffset="0" yoffset="0" xadvance="16" page="0" chnl="0" letter="⅛"/>
        <char id="8540" x="501" y="169" width="16" height="20" xoffset="0" yoffset="0" xadvance="16" page="0" chnl="0" letter="⅜"/>
        <char id="8541" x="521" y="169" width="16" height="20" xoffset="0" yoffset="0" xadvance="16" page="0" chnl="0" letter="⅝"/>
        <char id="8542" x="541" y="169" width="20" height="20" xoffset="0" yoffset="0" xadvance="20" page="0" chnl="0" letter="⅞"/>
        <char id="8592" x="565" y="169" width="13" height="20" xoffset="0" yoffset="0" xadvance="13" page="0" chnl="0" letter="←"/>
        <char id="8593" x="582" y="169" width="12" height="20" xoffset="0" yoffset="0" xadvance="12" page="0" chnl="0" letter="↑"/>
        <char id="8594" x="598" y="169" width="13" height="20" xoffset="0" yoffset="0" xadvance="13" page="0" chnl="0" letter="→"/>
        <char id="8595" x="615" y="169" width="12" height="20" xoffset="0" yoffset="0" xadvance="12" page="0" chnl="0" letter="↓"/>
        <char id="8596" x="631" y="169" width="17" height="20" xoffset="0" yoffset="0" xadvance="17" page="0" chnl="0" letter="↔"/>
        <char id="8597" x="652" y="169" width="12" height="20" xoffset="0" yoffset="0" xadvance="12" page="0" chnl="0" letter="↕"/>
        <char id="8598" x="668" y="169" width="11" height="20" xoffset="0" yoffset="0" xadvance="11" page="0" chnl="0" letter="↖"/>
        <char id="8599" x="683" y="169" width="11" height="20" xoffset="0" yoffset="0" xadvance="11" page="0" chnl="0" letter="↗"/>
        <char id="8600" x="698" y="169" width="11" height="20" xoffset="0" yoffset="0" xadvance="11" page="0" chnl="0" letter="↘"/>
        <char id="8601" x="713" y="169" width="11" height="20" xoffset="0" yoffset="0" xadvance="11" page="0" chnl="0" letter="↙"/>
        <char id="8605" x="728" y="169" width="11" height="20" xoffset="0" yoffset="0" xadvance="11" page="0" chnl="0" letter="↝"/>
        <char id="8617" x="743" y="169" width="11" height="20" xoffset="0" yoffset="0" xadvance="11" page="0" chnl="0" letter="↩"/>
        <char id="8618" x="758" y="169" width="11" height="20" xoffset="0" yoffset="0" xadvance="11" page="0" chnl="0" letter="↪"/>
        <char id="8624" x="773" y="169" width="11" height="20" xoffset="0" yoffset="0" xadvance="11" page="0" chnl="0" letter="↰"/>
        <char id="8625" x="788" y="169" width="11" height="20" xoffset="0" yoffset="0" xadvance="11" page="0" chnl="0" letter="↱"/>
        <char id="8626" x="683" y="241" width="7" height="20" xoffset="0" yoffset="0" xadvance="7" page="0" chnl="0" letter="↲"/>
        <char id="8627" x="803" y="169" width="11" height="20" xoffset="0" yoffset="0" xadvance="11" page="0" chnl="0" letter="↳"/>
        <char id="8628" x="818" y="169" width="11" height="20" xoffset="0" yoffset="0" xadvance="11" page="0" chnl="0" letter="↴"/>
        <char id="8629" x="833" y="169" width="11" height="20" xoffset="0" yoffset="0" xadvance="11" page="0" chnl="0" letter="↵"/>
        <char id="8676" x="848" y="169" width="11" height="20" xoffset="0" yoffset="0" xadvance="11" page="0" chnl="0" letter="⇤"/>
        <char id="8677" x="863" y="169" width="11" height="20" xoffset="0" yoffset="0" xadvance="11" page="0" chnl="0" letter="⇥"/>
        <char id="8678" x="683" y="241" width="7" height="20" xoffset="0" yoffset="0" xadvance="7" page="0" chnl="0" letter="⇦"/>
        <char id="8679" x="878" y="169" width="13" height="20" xoffset="0" yoffset="0" xadvance="13" page="0" chnl="0" letter="⇧"/>
        <char id="8706" x="895" y="169" width="10" height="20" xoffset="0" yoffset="0" xadvance="10" page="0" chnl="0" letter="∂"/>
        <char id="8707" x="683" y="241" width="7" height="20" xoffset="0" yoffset="0" xadvance="7" page="0" chnl="0" letter="∃"/>
        <char id="8708" x="683" y="241" width="7" height="20" xoffset="0" yoffset="0" xadvance="7" page="0" chnl="0" letter="∄"/>
        <char id="8709" x="683" y="241" width="7" height="20" xoffset="0" yoffset="0" xadvance="7" page="0" chnl="0" letter="∅"/>
        <char id="8710" x="909" y="169" width="11" height="20" xoffset="0" yoffset="0" xadvance="11" page="0" chnl="0" letter="∆"/>
        <char id="8719" x="924" y="169" width="10" height="20" xoffset="0" yoffset="0" xadvance="10" page="0" chnl="0" letter="∏"/>
        <char id="8720" x="683" y="241" width="7" height="20" xoffset="0" yoffset="0" xadvance="7" page="0" chnl="0" letter="∐"/>
        <char id="8721" x="938" y="169" width="9" height="20" xoffset="0" yoffset="0" xadvance="9" page="0" chnl="0" letter="∑"/>
        <char id="8722" x="951" y="169" width="10" height="20" xoffset="0" yoffset="0" xadvance="10" page="0" chnl="0" letter="−"/>
        <char id="8730" x="965" y="169" width="10" height="20" xoffset="0" yoffset="0" xadvance="10" page="0" chnl="0" letter="√"/>
        <char id="8731" x="683" y="241" width="7" height="20" xoffset="0" yoffset="0" xadvance="7" page="0" chnl="0" letter="∛"/>
        <char id="8732" x="683" y="241" width="7" height="20" xoffset="0" yoffset="0" xadvance="7" page="0" chnl="0" letter="∜"/>
        <char id="8733" x="683" y="241" width="7" height="20" xoffset="0" yoffset="0" xadvance="7" page="0" chnl="0" letter="∝"/>
        <char id="8734" x="979" y="169" width="14" height="20" xoffset="0" yoffset="0" xadvance="14" page="0" chnl="0" letter="∞"/>
        <char id="8747" x="997" y="169" width="7" height="20" xoffset="0" yoffset="0" xadvance="7" page="0" chnl="0" letter="∫"/>
        <char id="8776" x="1008" y="169" width="9" height="20" xoffset="0" yoffset="0" xadvance="9" page="0" chnl="0" letter="≈"/>
        <char id="8800" x="1" y="193" width="10" height="20" xoffset="0" yoffset="0" xadvance="10" page="0" chnl="0" letter="≠"/>
        <char id="8801" x="683" y="241" width="7" height="20" xoffset="0" yoffset="0" xadvance="7" page="0" chnl="0" letter="≡"/>
        <char id="8802" x="683" y="241" width="7" height="20" xoffset="0" yoffset="0" xadvance="7" page="0" chnl="0" letter="≢"/>
        <char id="8803" x="683" y="241" width="7" height="20" xoffset="0" yoffset="0" xadvance="7" page="0" chnl="0" letter="≣"/>
        <char id="8804" x="15" y="193" width="10" height="20" xoffset="0" yoffset="0" xadvance="10" page="0" chnl="0" letter="≤"/>
        <char id="8805" x="29" y="193" width="10" height="20" xoffset="0" yoffset="0" xadvance="10" page="0" chnl="0" letter="≥"/>
        <char id="9166" x="43" y="193" width="14" height="20" xoffset="0" yoffset="0" xadvance="14" page="0" chnl="0" letter="⏎"/>
        <char id="9227" x="61" y="193" width="10" height="20" xoffset="0" yoffset="0" xadvance="10" page="0" chnl="0" letter="␋"/>
        <char id="9228" x="75" y="193" width="10" height="20" xoffset="0" yoffset="0" xadvance="10" page="0" chnl="0" letter="␌"/>
        <char id="9312" x="89" y="193" width="14" height="20" xoffset="0" yoffset="0" xadvance="14" page="0" chnl="0" letter="①"/>
        <char id="9313" x="107" y="193" width="14" height="20" xoffset="0" yoffset="0" xadvance="14" page="0" chnl="0" letter="②"/>
        <char id="9314" x="125" y="193" width="14" height="20" xoffset="0" yoffset="0" xadvance="14" page="0" chnl="0" letter="③"/>
        <char id="9315" x="143" y="193" width="14" height="20" xoffset="0" yoffset="0" xadvance="14" page="0" chnl="0" letter="④"/>
        <char id="9316" x="161" y="193" width="14" height="20" xoffset="0" yoffset="0" xadvance="14" page="0" chnl="0" letter="⑤"/>
        <char id="9317" x="179" y="193" width="14" height="20" xoffset="0" yoffset="0" xadvance="14" page="0" chnl="0" letter="⑥"/>
        <char id="9318" x="197" y="193" width="14" height="20" xoffset="0" yoffset="0" xadvance="14" page="0" chnl="0" letter="⑦"/>
        <char id="9319" x="215" y="193" width="14" height="20" xoffset="0" yoffset="0" xadvance="14" page="0" chnl="0" letter="⑧"/>
        <char id="9320" x="233" y="193" width="14" height="20" xoffset="0" yoffset="0" xadvance="14" page="0" chnl="0" letter="⑨"/>
        <char id="9450" x="251" y="193" width="14" height="20" xoffset="0" yoffset="0" xadvance="14" page="0" chnl="0" letter="⓪"/>
        <char id="9471" x="269" y="193" width="14" height="20" xoffset="0" yoffset="0" xadvance="14" page="0" chnl="0" letter="⓿"/>
        <char id="9650" x="287" y="193" width="14" height="20" xoffset="0" yoffset="0" xadvance="14" page="0" chnl="0" letter="▲"/>
        <char id="9651" x="305" y="193" width="14" height="20" xoffset="0" yoffset="0" xadvance="14" page="0" chnl="0" letter="△"/>
        <char id="9652" x="683" y="241" width="7" height="20" xoffset="0" yoffset="0" xadvance="7" page="0" chnl="0" letter="▴"/>
        <char id="9653" x="683" y="241" width="7" height="20" xoffset="0" yoffset="0" xadvance="7" page="0" chnl="0" letter="▵"/>
        <char id="9654" x="323" y="193" width="14" height="20" xoffset="0" yoffset="0" xadvance="14" page="0" chnl="0" letter="▶"/>
        <char id="9655" x="341" y="193" width="14" height="20" xoffset="0" yoffset="0" xadvance="14" page="0" chnl="0" letter="▷"/>
        <char id="9660" x="359" y="193" width="14" height="20" xoffset="0" yoffset="0" xadvance="14" page="0" chnl="0" letter="▼"/>
        <char id="9661" x="377" y="193" width="14" height="20" xoffset="0" yoffset="0" xadvance="14" page="0" chnl="0" letter="▽"/>
        <char id="9662" x="683" y="241" width="7" height="20" xoffset="0" yoffset="0" xadvance="7" page="0" chnl="0" letter="▾"/>
        <char id="9663" x="683" y="241" width="7" height="20" xoffset="0" yoffset="0" xadvance="7" page="0" chnl="0" letter="▿"/>
        <char id="9664" x="395" y="193" width="14" height="20" xoffset="0" yoffset="0" xadvance="14" page="0" chnl="0" letter="◀"/>
        <char id="9665" x="413" y="193" width="14" height="20" xoffset="0" yoffset="0" xadvance="14" page="0" chnl="0" letter="◁"/>
        <char id="9674" x="431" y="193" width="9" height="20" xoffset="0" yoffset="0" xadvance="9" page="0" chnl="0" letter="◊"/>
        <char id="9675" x="444" y="193" width="14" height="20" xoffset="0" yoffset="0" xadvance="14" page="0" chnl="0" letter="○"/>
        <char id="9676" x="462" y="193" width="14" height="20" xoffset="0" yoffset="0" xadvance="14" page="0" chnl="0" letter="◌"/>
        <char id="9677" x="683" y="241" width="7" height="20" xoffset="0" yoffset="0" xadvance="7" page="0" chnl="0" letter="◍"/>
        <char id="9678" x="683" y="241" width="7" height="20" xoffset="0" yoffset="0" xadvance="7" page="0" chnl="0" letter="◎"/>
        <char id="9679" x="480" y="193" width="14" height="20" xoffset="0" yoffset="0" xadvance="14" page="0" chnl="0" letter="●"/>
        <char id="9785" x="498" y="193" width="14" height="20" xoffset="0" yoffset="0" xadvance="14" page="0" chnl="0" letter="☹"/>
        <char id="9786" x="516" y="193" width="14" height="20" xoffset="0" yoffset="0" xadvance="14" page="0" chnl="0" letter="☺"/>
        <char id="10102" x="534" y="193" width="14" height="20" xoffset="0" yoffset="0" xadvance="14" page="0" chnl="0" letter="❶"/>
        <char id="10103" x="552" y="193" width="14" height="20" xoffset="0" yoffset="0" xadvance="14" page="0" chnl="0" letter="❷"/>
        <char id="10104" x="570" y="193" width="14" height="20" xoffset="0" yoffset="0" xadvance="14" page="0" chnl="0" letter="❸"/>
        <char id="10105" x="588" y="193" width="14" height="20" xoffset="0" yoffset="0" xadvance="14" page="0" chnl="0" letter="❹"/>
        <char id="10106" x="606" y="193" width="14" height="20" xoffset="0" yoffset="0" xadvance="14" page="0" chnl="0" letter="❺"/>
        <char id="10107" x="624" y="193" width="14" height="20" xoffset="0" yoffset="0" xadvance="14" page="0" chnl="0" letter="❻"/>
        <char id="10108" x="642" y="193" width="14" height="20" xoffset="0" yoffset="0" xadvance="14" page="0" chnl="0" letter="❼"/>
        <char id="10109" x="660" y="193" width="14" height="20" xoffset="0" yoffset="0" xadvance="14" page="0" chnl="0" letter="❽"/>
        <char id="10110" x="678" y="193" width="14" height="20" xoffset="0" yoffset="0" xadvance="14" page="0" chnl="0" letter="❾"/>
        <char id="12290" x="696" y="193" width="6" height="20" xoffset="0" yoffset="0" xadvance="6" page="0" chnl="0" letter="。"/>
        <char id="12291" x="706" y="193" width="6" height="20" xoffset="0" yoffset="0" xadvance="6" page="0" chnl="0" letter="〃"/>
        <char id="12296" x="716" y="193" width="6" height="20" xoffset="0" yoffset="0" xadvance="6" page="0" chnl="0" letter="〈"/>
        <char id="12297" x="726" y="193" width="6" height="20" xoffset="0" yoffset="0" xadvance="6" page="0" chnl="0" letter="〉"/>
        <char id="12298" x="736" y="193" width="9" height="20" xoffset="0" yoffset="0" xadvance="9" page="0" chnl="0" letter="《"/>
        <char id="12299" x="749" y="193" width="9" height="20" xoffset="0" yoffset="0" xadvance="9" page="0" chnl="0" letter="》"/>
        <char id="12300" x="762" y="193" width="7" height="20" xoffset="0" yoffset="0" xadvance="7" page="0" chnl="0" letter="「"/>
        <char id="12301" x="773" y="193" width="7" height="20" xoffset="0" yoffset="0" xadvance="7" page="0" chnl="0" letter="」"/>
        <char id="12302" x="784" y="193" width="7" height="20" xoffset="0" yoffset="0" xadvance="7" page="0" chnl="0" letter="『"/>
        <char id="12303" x="795" y="193" width="7" height="20" xoffset="0" yoffset="0" xadvance="7" page="0" chnl="0" letter="』"/>
        <char id="12304" x="806" y="193" width="6" height="20" xoffset="0" yoffset="0" xadvance="6" page="0" chnl="0" letter="【"/>
        <char id="12305" x="816" y="193" width="6" height="20" xoffset="0" yoffset="0" xadvance="6" page="0" chnl="0" letter="】"/>
        <char id="12308" x="826" y="193" width="7" height="20" xoffset="0" yoffset="0" xadvance="7" page="0" chnl="0" letter="〔"/>
        <char id="12309" x="837" y="193" width="7" height="20" xoffset="0" yoffset="0" xadvance="7" page="0" chnl="0" letter="〕"/>
        <char id="12310" x="848" y="193" width="6" height="20" xoffset="0" yoffset="0" xadvance="6" page="0" chnl="0" letter="〖"/>
        <char id="12311" x="858" y="193" width="6" height="20" xoffset="0" yoffset="0" xadvance="6" page="0" chnl="0" letter="〗"/>
        <char id="12316" x="868" y="193" width="14" height="20" xoffset="0" yoffset="0" xadvance="14" page="0" chnl="0" letter="〜"/>
        <char id="42891" x="886" y="193" width="3" height="20" xoffset="0" yoffset="0" xadvance="3" page="0" chnl="0" letter="Ꞌ"/>
        <char id="42892" x="893" y="193" width="3" height="20" xoffset="0" yoffset="0" xadvance="3" page="0" chnl="0" letter="ꞌ"/>
        <char id="65281" x="900" y="193" width="5" height="20" xoffset="0" yoffset="0" xadvance="5" page="0" chnl="0" letter="！"/>
        <char id="65282" x="909" y="193" width="6" height="20" xoffset="0" yoffset="0" xadvance="6" page="0" chnl="0" letter="＂"/>
        <char id="65283" x="919" y="193" width="8" height="20" xoffset="0" yoffset="0" xadvance="8" page="0" chnl="0" letter="＃"/>
        <char id="65284" x="683" y="241" width="7" height="20" xoffset="0" yoffset="0" xadvance="7" page="0" chnl="0" letter="＄"/>
        <char id="65285" x="931" y="193" width="13" height="20" xoffset="0" yoffset="0" xadvance="13" page="0" chnl="0" letter="％"/>
        <char id="65286" x="948" y="193" width="11" height="20" xoffset="0" yoffset="0" xadvance="11" page="0" chnl="0" letter="＆"/>
        <char id="65287" x="963" y="193" width="3" height="20" xoffset="0" yoffset="0" xadvance="3" page="0" chnl="0" letter="＇"/>
        <char id="65288" x="970" y="193" width="5" height="20" xoffset="0" yoffset="0" xadvance="5" page="0" chnl="0" letter="（"/>
        <char id="65289" x="979" y="193" width="5" height="20" xoffset="0" yoffset="0" xadvance="5" page="0" chnl="0" letter="）"/>
        <char id="65290" x="988" y="193" width="7" height="20" xoffset="0" yoffset="0" xadvance="7" page="0" chnl="0" letter="＊"/>
        <char id="65291" x="683" y="241" width="7" height="20" xoffset="0" yoffset="0" xadvance="7" page="0" chnl="0" letter="＋"/>
        <char id="65292" x="999" y="193" width="4" height="20" xoffset="0" yoffset="0" xadvance="4" page="0" chnl="0" letter="，"/>
        <char id="65293" x="1007" y="193" width="12" height="20" xoffset="0" yoffset="0" xadvance="12" page="0" chnl="0" letter="－"/>
        <char id="65294" x="1" y="217" width="4" height="20" xoffset="0" yoffset="0" xadvance="4" page="0" chnl="0" letter="．"/>
        <char id="65295" x="9" y="217" width="8" height="20" xoffset="0" yoffset="0" xadvance="8" page="0" chnl="0" letter="／"/>
        <char id="65306" x="21" y="217" width="4" height="20" xoffset="0" yoffset="0" xadvance="4" page="0" chnl="0" letter="："/>
        <char id="65307" x="29" y="217" width="4" height="20" xoffset="0" yoffset="0" xadvance="4" page="0" chnl="0" letter="；"/>
        <char id="65308" x="683" y="241" width="7" height="20" xoffset="0" yoffset="0" xadvance="7" page="0" chnl="0" letter="＜"/>
        <char id="65309" x="683" y="241" width="7" height="20" xoffset="0" yoffset="0" xadvance="7" page="0" chnl="0" letter="＝"/>
        <char id="65310" x="683" y="241" width="7" height="20" xoffset="0" yoffset="0" xadvance="7" page="0" chnl="0" letter="＞"/>
        <char id="65311" x="37" y="217" width="10" height="20" xoffset="0" yoffset="0" xadvance="10" page="0" chnl="0" letter="？"/>
        <char id="65312" x="51" y="217" width="15" height="20" xoffset="0" yoffset="0" xadvance="15" page="0" chnl="0" letter="＠"/>
        <char id="65339" x="70" y="217" width="6" height="20" xoffset="0" yoffset="0" xadvance="6" page="0" chnl="0" letter="［"/>
        <char id="65340" x="80" y="217" width="8" height="20" xoffset="0" yoffset="0" xadvance="8" page="0" chnl="0" letter="＼"/>
        <char id="65341" x="92" y="217" width="6" height="20" xoffset="0" yoffset="0" xadvance="6" page="0" chnl="0" letter="］"/>
        <char id="65342" x="683" y="241" width="7" height="20" xoffset="0" yoffset="0" xadvance="7" page="0" chnl="0" letter="＾"/>
        <char id="65343" x="102" y="217" width="10" height="20" xoffset="0" yoffset="0" xadvance="10" page="0" chnl="0" letter="＿"/>
        <char id="65371" x="116" y="217" width="7" height="20" xoffset="0" yoffset="0" xadvance="7" page="0" chnl="0" letter="｛"/>
        <char id="65372" x="683" y="241" width="7" height="20" xoffset="0" yoffset="0" xadvance="7" page="0" chnl="0" letter="｜"/>
        <char id="65373" x="127" y="217" width="7" height="20" xoffset="0" yoffset="0" xadvance="7" page="0" chnl="0" letter="｝"/>
    </chars>
    <kernings count="0"></kernings>
</font>